{
  "bids": [
    {
      "admin": "zpressley",
      "amount": 10,
      "bid_id": "bid-75d5ab0ed795",
      "bid_type": "OB",
      "date": "2026-03-30",
      "prospect_id": "7066",
      "source": "admin",
      "team": "HAM",
      "timestamp": "2026-03-31T03:51:04.941413+00:00"
    },
    {
      "admin": "zpressley",
      "amount": 10,
      "bid_id": "bid-7d5fb3f2d301",
      "bid_type": "OB",
      "date": "2026-03-30",
      "prospect_id": "4634",
      "source": "admin",
      "team": "DRO",
      "timestamp": "2026-03-31T03:55:59.739546+00:00"
    }
  ],
  "last_updated": "2026-03-31T03:55:59.739546+00:00",
  "matches": [],
  "phase": "ob_window",
  "priority_order": [
    "DMN",
    "DRO",
    "CFL",
    "SAD",
    "WAR",
    "JEP",
    "RV",
    "HAM",
    "TBB",
    "LFB",
    "B2J",
    "WIZ"
  ],
  "schedule_meta": {
    "all_star_break_start": "2026-07-13",
    "auction_restart": "2026-07-20",
    "playoffs_start": "2026-09-07",
    "season_start": "2026-03-16"
  },
  "week_start": "2026-03-30"
}