{
  "updated_at": "2026-04-25T06:43:12.583549-04:00",
  "yahoo_farm_upids": {
    "WIZ": [
      "6591",
      "7612",
      "4443",
      "6263"
    ],
    "B2J": [
      "3790"
    ],
    "CFL": [
      "2979",
      "3895",
      "2237"
    ],
    "RV": [
      "3779",
      "7568",
      "3934",
      "7602"
    ],
    "JEP": [
      "3906",
      "3921",
      "6720"
    ],
    "TBB": [
      "6853",
      "3678"
    ],
    "DRO": [
      "7173",
      "3852",
      "4611"
    ],
    "SAD": [
      "3951",
      "6516",
      "7924"
    ],
    "WAR": [
      "3914",
      "3522",
      "3903",
      "3484",
      "7135"
    ],
    "DMN": [
      "7619"
    ]
  }
}