{
  "date": "2026-05-13",
  "week": 8,
  "stat_categories": [
    {
      "stat_id": "60",
      "display_name": "H/AB",
      "name": "Hits / At Bats",
      "display_only": true
    },
    {
      "stat_id": "7",
      "display_name": "R",
      "name": "Runs",
      "display_only": false
    },
    {
      "stat_id": "8",
      "display_name": "H",
      "name": "Hits",
      "display_only": false
    },
    {
      "stat_id": "12",
      "display_name": "HR",
      "name": "Home Runs",
      "display_only": false
    },
    {
      "stat_id": "13",
      "display_name": "RBI",
      "name": "Runs Batted In",
      "display_only": false
    },
    {
      "stat_id": "16",
      "display_name": "SB",
      "name": "Stolen Bases",
      "display_only": false
    },
    {
      "stat_id": "18",
      "display_name": "BB",
      "name": "Walks",
      "display_only": false
    },
    {
      "stat_id": "21",
      "display_name": "K",
      "name": "Strikeouts",
      "display_only": false
    },
    {
      "stat_id": "23",
      "display_name": "TB",
      "name": "Total Bases",
      "display_only": false
    },
    {
      "stat_id": "3",
      "display_name": "AVG",
      "name": "Batting Average",
      "display_only": false
    },
    {
      "stat_id": "55",
      "display_name": "OPS",
      "name": "On-base + Slugging Percentage",
      "display_only": false
    },
    {
      "stat_id": "24",
      "display_name": "APP",
      "name": "Pitching Appearances",
      "display_only": false
    },
    {
      "stat_id": "50",
      "display_name": "IP",
      "name": "Innings Pitched",
      "display_only": true
    },
    {
      "stat_id": "37",
      "display_name": "ER",
      "name": "Earned Runs",
      "display_only": false
    },
    {
      "stat_id": "38",
      "display_name": "P_HR",
      "name": "Home Runs",
      "display_only": false
    },
    {
      "stat_id": "42",
      "display_name": "P_K",
      "name": "Strikeouts",
      "display_only": false
    },
    {
      "stat_id": "49",
      "display_name": "P_TB",
      "name": "Total Bases Allowed",
      "display_only": false
    },
    {
      "stat_id": "26",
      "display_name": "ERA",
      "name": "Earned Run Average",
      "display_only": false
    },
    {
      "stat_id": "57",
      "display_name": "K/9",
      "name": "Strikeouts per Nine Innings",
      "display_only": false
    },
    {
      "stat_id": "77",
      "display_name": "H/9",
      "name": "Hits Per Nine Innings",
      "display_only": false
    },
    {
      "stat_id": "78",
      "display_name": "BB/9",
      "name": "Walks Per Nine Innings",
      "display_only": false
    },
    {
      "stat_id": "83",
      "display_name": "QS",
      "name": "Quality Starts",
      "display_only": false
    }
  ],
  "standings": [
    {
      "rank": 1,
      "manager": "HAM",
      "team": "HAM",
      "record": "83-51-6",
      "win_pct": 0.614,
      "opponent": "WIZ",
      "score": "12",
      "opponent_score": "6",
      "ties": "2",
      "live_record": "12-6-2",
      "live_win_pct": 0.65,
      "categories": {
        "H/AB": "13/59",
        "R": "11",
        "H": "13",
        "HR": "2",
        "RBI": "6",
        "SB": "3",
        "BB": "5",
        "K": "15",
        "TB": "20",
        "AVG": ".220",
        "OPS": ".653",
        "APP": "4",
        "IP": "14.0",
        "ER": "9",
        "P_HR": "3",
        "P_K": "14",
        "P_TB": "19",
        "ERA": "5.79",
        "K/9": "9.00",
        "H/9": "6.43",
        "BB/9": "3.86",
        "QS": "1"
      },
      "overall_live_record": "95-57-8",
      "overall_live_win_pct": 0.619,
      "live_rank": 2
    },
    {
      "rank": 2,
      "manager": "DMN",
      "team": "DMN",
      "record": "72-61-7",
      "win_pct": 0.539,
      "opponent": "CFL",
      "score": "12",
      "opponent_score": "5",
      "ties": "3",
      "live_record": "12-5-3",
      "live_win_pct": 0.675,
      "categories": {
        "H/AB": "16/48",
        "R": "9",
        "H": "16",
        "HR": "3",
        "RBI": "6",
        "SB": "1",
        "BB": "11",
        "K": "10",
        "TB": "28",
        "AVG": ".333",
        "OPS": "1.041",
        "APP": "4",
        "IP": "7.2",
        "ER": "2",
        "P_HR": "0",
        "P_K": "7",
        "P_TB": "9",
        "ERA": "2.35",
        "K/9": "8.22",
        "H/9": "7.04",
        "BB/9": "1.17",
        "QS": "0"
      },
      "overall_live_record": "84-66-10",
      "overall_live_win_pct": 0.556,
      "live_rank": 3
    },
    {
      "rank": 3,
      "manager": "WIZ",
      "team": "WIZ",
      "record": "68-64-8",
      "win_pct": 0.514,
      "opponent": "HAM",
      "score": "6",
      "opponent_score": "12",
      "ties": "2",
      "live_record": "6-12-2",
      "live_win_pct": 0.35,
      "categories": {
        "H/AB": "11/58",
        "R": "6",
        "H": "11",
        "HR": "1",
        "RBI": "3",
        "SB": "2",
        "BB": "6",
        "K": "15",
        "TB": "18",
        "AVG": ".190",
        "OPS": ".572",
        "APP": "6",
        "IP": "6.0",
        "ER": "2",
        "P_HR": "0",
        "P_K": "6",
        "P_TB": "7",
        "ERA": "3.00",
        "K/9": "9.00",
        "H/9": "7.50",
        "BB/9": "6.00",
        "QS": "0"
      },
      "overall_live_record": "74-76-10",
      "overall_live_win_pct": 0.494,
      "live_rank": 6
    },
    {
      "rank": 4,
      "manager": "LFB",
      "team": "LFB",
      "record": "81-53-6",
      "win_pct": 0.6,
      "opponent": "B2J",
      "score": "17",
      "opponent_score": "3",
      "ties": "0",
      "live_record": "17-3-0",
      "live_win_pct": 0.85,
      "categories": {
        "H/AB": "15/61",
        "R": "11",
        "H": "15",
        "HR": "3",
        "RBI": "8",
        "SB": "2",
        "BB": "5",
        "K": "14",
        "TB": "27",
        "AVG": ".246",
        "OPS": ".756",
        "APP": "6",
        "IP": "9.1",
        "ER": "3",
        "P_HR": "0",
        "P_K": "13",
        "P_TB": "5",
        "ERA": "2.89",
        "K/9": "12.54",
        "H/9": "4.82",
        "BB/9": "1.93",
        "QS": "0"
      },
      "overall_live_record": "98-56-6",
      "overall_live_win_pct": 0.631,
      "live_rank": 1
    },
    {
      "rank": 5,
      "manager": "TBB",
      "team": "TBB",
      "record": "73-61-6",
      "win_pct": 0.543,
      "opponent": "WAR",
      "score": "5",
      "opponent_score": "14",
      "ties": "1",
      "live_record": "5-14-1",
      "live_win_pct": 0.275,
      "categories": {
        "H/AB": "8/44",
        "R": "3",
        "H": "8",
        "HR": "0",
        "RBI": "3",
        "SB": "1",
        "BB": "1",
        "K": "10",
        "TB": "10",
        "AVG": ".182",
        "OPS": ".427",
        "APP": "4",
        "IP": "16.0",
        "ER": "1",
        "P_HR": "0",
        "P_K": "15",
        "P_TB": "15",
        "ERA": "0.56",
        "K/9": "8.44",
        "H/9": "5.63",
        "BB/9": "1.13",
        "QS": "2"
      },
      "overall_live_record": "78-75-7",
      "overall_live_win_pct": 0.509,
      "live_rank": 4
    },
    {
      "rank": 6,
      "manager": "CFL",
      "team": "CFL",
      "record": "67-66-7",
      "win_pct": 0.504,
      "opponent": "DMN",
      "score": "5",
      "opponent_score": "12",
      "ties": "3",
      "live_record": "5-12-3",
      "live_win_pct": 0.325,
      "categories": {
        "H/AB": "10/49",
        "R": "5",
        "H": "10",
        "HR": "3",
        "RBI": "6",
        "SB": "2",
        "BB": "6",
        "K": "9",
        "TB": "20",
        "AVG": ".204",
        "OPS": ".699",
        "APP": "6",
        "IP": "13.1",
        "ER": "6",
        "P_HR": "1",
        "P_K": "16",
        "P_TB": "19",
        "ERA": "4.05",
        "K/9": "10.80",
        "H/9": "10.13",
        "BB/9": "4.73",
        "QS": "0"
      },
      "overall_live_record": "72-78-10",
      "overall_live_win_pct": 0.481,
      "live_rank": 8
    },
    {
      "rank": 7,
      "manager": "B2J",
      "team": "B2J",
      "record": "61-68-11",
      "win_pct": 0.475,
      "opponent": "LFB",
      "score": "3",
      "opponent_score": "17",
      "ties": "0",
      "live_record": "3-17-0",
      "live_win_pct": 0.15,
      "categories": {
        "H/AB": "10/51",
        "R": "6",
        "H": "10",
        "HR": "1",
        "RBI": "2",
        "SB": "0",
        "BB": "4",
        "K": "12",
        "TB": "13",
        "AVG": ".196",
        "OPS": ".509",
        "APP": "4",
        "IP": "13.2",
        "ER": "8",
        "P_HR": "2",
        "P_K": "11",
        "P_TB": "27",
        "ERA": "5.27",
        "K/9": "7.24",
        "H/9": "11.85",
        "BB/9": "0.66",
        "QS": "1"
      },
      "overall_live_record": "64-85-11",
      "overall_live_win_pct": 0.434,
      "live_rank": 11
    },
    {
      "rank": 8,
      "manager": "RV",
      "team": "RV",
      "record": "61-70-9",
      "win_pct": 0.468,
      "opponent": "SAD",
      "score": "4",
      "opponent_score": "12",
      "ties": "4",
      "live_record": "4-12-4",
      "live_win_pct": 0.3,
      "categories": {
        "H/AB": "14/53",
        "R": "6",
        "H": "14",
        "HR": "1",
        "RBI": "7",
        "SB": "0",
        "BB": "6",
        "K": "12",
        "TB": "22",
        "AVG": ".264",
        "OPS": ".765",
        "APP": "4",
        "IP": "8.0",
        "ER": "5",
        "P_HR": "1",
        "P_K": "8",
        "P_TB": "13",
        "ERA": "5.63",
        "K/9": "9.00",
        "H/9": "9.00",
        "BB/9": "6.75",
        "QS": "1"
      },
      "overall_live_record": "65-82-13",
      "overall_live_win_pct": 0.447,
      "live_rank": 10
    },
    {
      "rank": 9,
      "manager": "WAR",
      "team": "WAR",
      "record": "61-71-8",
      "win_pct": 0.464,
      "opponent": "TBB",
      "score": "14",
      "opponent_score": "5",
      "ties": "1",
      "live_record": "14-5-1",
      "live_win_pct": 0.725,
      "categories": {
        "H/AB": "9/43",
        "R": "5",
        "H": "9",
        "HR": "1",
        "RBI": "4",
        "SB": "0",
        "BB": "5",
        "K": "7",
        "TB": "14",
        "AVG": ".209",
        "OPS": ".617",
        "APP": "6",
        "IP": "16.2",
        "ER": "4",
        "P_HR": "1",
        "P_K": "21",
        "P_TB": "9",
        "ERA": "2.16",
        "K/9": "11.34",
        "H/9": "3.24",
        "BB/9": "3.24",
        "QS": "2"
      },
      "overall_live_record": "75-76-9",
      "overall_live_win_pct": 0.497,
      "live_rank": 5
    },
    {
      "rank": 10,
      "manager": "JEP",
      "team": "JEP",
      "record": "58-71-11",
      "win_pct": 0.454,
      "opponent": "DRO",
      "score": "6",
      "opponent_score": "10",
      "ties": "4",
      "live_record": "6-10-4",
      "live_win_pct": 0.4,
      "categories": {
        "H/AB": "11/42",
        "R": "4",
        "H": "11",
        "HR": "1",
        "RBI": "4",
        "SB": "1",
        "BB": "6",
        "K": "15",
        "TB": "16",
        "AVG": ".262",
        "OPS": ".741",
        "APP": "4",
        "IP": "12.1",
        "ER": "7",
        "P_HR": "4",
        "P_K": "14",
        "P_TB": "23",
        "ERA": "5.11",
        "K/9": "10.22",
        "H/9": "6.57",
        "BB/9": "2.92",
        "QS": "0"
      },
      "overall_live_record": "64-81-15",
      "overall_live_win_pct": 0.447,
      "live_rank": 9
    },
    {
      "rank": 11,
      "manager": "SAD",
      "team": "SAD",
      "record": "58-72-10",
      "win_pct": 0.45,
      "opponent": "RV",
      "score": "12",
      "opponent_score": "4",
      "ties": "4",
      "live_record": "12-4-4",
      "live_win_pct": 0.7,
      "categories": {
        "H/AB": "18/64",
        "R": "9",
        "H": "18",
        "HR": "2",
        "RBI": "6",
        "SB": "0",
        "BB": "4",
        "K": "14",
        "TB": "27",
        "AVG": ".281",
        "OPS": ".750",
        "APP": "4",
        "IP": "14.1",
        "ER": "5",
        "P_HR": "1",
        "P_K": "20",
        "P_TB": "12",
        "ERA": "3.14",
        "K/9": "12.56",
        "H/9": "4.40",
        "BB/9": "3.14",
        "QS": "2"
      },
      "overall_live_record": "70-76-14",
      "overall_live_win_pct": 0.481,
      "live_rank": 7
    },
    {
      "rank": 12,
      "manager": "DRO",
      "team": "DRO",
      "record": "48-83-9",
      "win_pct": 0.375,
      "opponent": "JEP",
      "score": "10",
      "opponent_score": "6",
      "ties": "4",
      "live_record": "10-6-4",
      "live_win_pct": 0.6,
      "categories": {
        "H/AB": "12/47",
        "R": "4",
        "H": "12",
        "HR": "1",
        "RBI": "6",
        "SB": "1",
        "BB": "8",
        "K": "13",
        "TB": "17",
        "AVG": ".255",
        "OPS": ".725",
        "APP": "2",
        "IP": "2.0",
        "ER": "1",
        "P_HR": "0",
        "P_K": "3",
        "P_TB": "3",
        "ERA": "4.50",
        "K/9": "13.50",
        "H/9": "9.00",
        "BB/9": "4.50",
        "QS": "0"
      },
      "overall_live_record": "58-89-13",
      "overall_live_win_pct": 0.403,
      "live_rank": 12
    }
  ],
  "matchups": [
    {
      "team1": {
        "team": "WIZ",
        "name": "Whiz Kids",
        "score": "6",
        "categories": {
          "H/AB": "11/58",
          "R": "6",
          "H": "11",
          "HR": "1",
          "RBI": "3",
          "SB": "2",
          "BB": "6",
          "K": "15",
          "TB": "18",
          "AVG": ".190",
          "OPS": ".572",
          "APP": "6",
          "IP": "6.0",
          "ER": "2",
          "P_HR": "0",
          "P_K": "6",
          "P_TB": "7",
          "ERA": "3.00",
          "K/9": "9.00",
          "H/9": "7.50",
          "BB/9": "6.00",
          "QS": "0"
        }
      },
      "team2": {
        "team": "HAM",
        "name": "Hammers",
        "score": "12",
        "categories": {
          "H/AB": "13/59",
          "R": "11",
          "H": "13",
          "HR": "2",
          "RBI": "6",
          "SB": "3",
          "BB": "5",
          "K": "15",
          "TB": "20",
          "AVG": ".220",
          "OPS": ".653",
          "APP": "4",
          "IP": "14.0",
          "ER": "9",
          "P_HR": "3",
          "P_K": "14",
          "P_TB": "19",
          "ERA": "5.79",
          "K/9": "9.00",
          "H/9": "6.43",
          "BB/9": "3.86",
          "QS": "1"
        }
      }
    },
    {
      "team1": {
        "team": "DRO",
        "name": "Andromedans",
        "score": "10",
        "categories": {
          "H/AB": "12/47",
          "R": "4",
          "H": "12",
          "HR": "1",
          "RBI": "6",
          "SB": "1",
          "BB": "8",
          "K": "13",
          "TB": "17",
          "AVG": ".255",
          "OPS": ".725",
          "APP": "2",
          "IP": "2.0",
          "ER": "1",
          "P_HR": "0",
          "P_K": "3",
          "P_TB": "3",
          "ERA": "4.50",
          "K/9": "13.50",
          "H/9": "9.00",
          "BB/9": "4.50",
          "QS": "0"
        }
      },
      "team2": {
        "team": "JEP",
        "name": "Jepordizers",
        "score": "6",
        "categories": {
          "H/AB": "11/42",
          "R": "4",
          "H": "11",
          "HR": "1",
          "RBI": "4",
          "SB": "1",
          "BB": "6",
          "K": "15",
          "TB": "16",
          "AVG": ".262",
          "OPS": ".741",
          "APP": "4",
          "IP": "12.1",
          "ER": "7",
          "P_HR": "4",
          "P_K": "14",
          "P_TB": "23",
          "ERA": "5.11",
          "K/9": "10.22",
          "H/9": "6.57",
          "BB/9": "2.92",
          "QS": "0"
        }
      }
    },
    {
      "team1": {
        "team": "B2J",
        "name": "Btwn2Jackies",
        "score": "3",
        "categories": {
          "H/AB": "10/51",
          "R": "6",
          "H": "10",
          "HR": "1",
          "RBI": "2",
          "SB": "0",
          "BB": "4",
          "K": "12",
          "TB": "13",
          "AVG": ".196",
          "OPS": ".509",
          "APP": "4",
          "IP": "13.2",
          "ER": "8",
          "P_HR": "2",
          "P_K": "11",
          "P_TB": "27",
          "ERA": "5.27",
          "K/9": "7.24",
          "H/9": "11.85",
          "BB/9": "0.66",
          "QS": "1"
        }
      },
      "team2": {
        "team": "LFB",
        "name": "La Flama Blanca",
        "score": "17",
        "categories": {
          "H/AB": "15/61",
          "R": "11",
          "H": "15",
          "HR": "3",
          "RBI": "8",
          "SB": "2",
          "BB": "5",
          "K": "14",
          "TB": "27",
          "AVG": ".246",
          "OPS": ".756",
          "APP": "6",
          "IP": "9.1",
          "ER": "3",
          "P_HR": "0",
          "P_K": "13",
          "P_TB": "5",
          "ERA": "2.89",
          "K/9": "12.54",
          "H/9": "4.82",
          "BB/9": "1.93",
          "QS": "0"
        }
      }
    },
    {
      "team1": {
        "team": "CFL",
        "name": "Country Fried Lamb",
        "score": "5",
        "categories": {
          "H/AB": "10/49",
          "R": "5",
          "H": "10",
          "HR": "3",
          "RBI": "6",
          "SB": "2",
          "BB": "6",
          "K": "9",
          "TB": "20",
          "AVG": ".204",
          "OPS": ".699",
          "APP": "6",
          "IP": "13.1",
          "ER": "6",
          "P_HR": "1",
          "P_K": "16",
          "P_TB": "19",
          "ERA": "4.05",
          "K/9": "10.80",
          "H/9": "10.13",
          "BB/9": "4.73",
          "QS": "0"
        }
      },
      "team2": {
        "team": "DMN",
        "name": "The Damn Yankees",
        "score": "12",
        "categories": {
          "H/AB": "16/48",
          "R": "9",
          "H": "16",
          "HR": "3",
          "RBI": "6",
          "SB": "1",
          "BB": "11",
          "K": "10",
          "TB": "28",
          "AVG": ".333",
          "OPS": "1.041",
          "APP": "4",
          "IP": "7.2",
          "ER": "2",
          "P_HR": "0",
          "P_K": "7",
          "P_TB": "9",
          "ERA": "2.35",
          "K/9": "8.22",
          "H/9": "7.04",
          "BB/9": "1.17",
          "QS": "0"
        }
      }
    },
    {
      "team1": {
        "team": "SAD",
        "name": "not much of a donkey",
        "score": "12",
        "categories": {
          "H/AB": "18/64",
          "R": "9",
          "H": "18",
          "HR": "2",
          "RBI": "6",
          "SB": "0",
          "BB": "4",
          "K": "14",
          "TB": "27",
          "AVG": ".281",
          "OPS": ".750",
          "APP": "4",
          "IP": "14.1",
          "ER": "5",
          "P_HR": "1",
          "P_K": "20",
          "P_TB": "12",
          "ERA": "3.14",
          "K/9": "12.56",
          "H/9": "4.40",
          "BB/9": "3.14",
          "QS": "2"
        }
      },
      "team2": {
        "team": "RV",
        "name": "Rick Vaughn",
        "score": "4",
        "categories": {
          "H/AB": "14/53",
          "R": "6",
          "H": "14",
          "HR": "1",
          "RBI": "7",
          "SB": "0",
          "BB": "6",
          "K": "12",
          "TB": "22",
          "AVG": ".264",
          "OPS": ".765",
          "APP": "4",
          "IP": "8.0",
          "ER": "5",
          "P_HR": "1",
          "P_K": "8",
          "P_TB": "13",
          "ERA": "5.63",
          "K/9": "9.00",
          "H/9": "9.00",
          "BB/9": "6.75",
          "QS": "1"
        }
      }
    },
    {
      "team1": {
        "team": "TBB",
        "name": "The Bluke Blokes",
        "score": "5",
        "categories": {
          "H/AB": "8/44",
          "R": "3",
          "H": "8",
          "HR": "0",
          "RBI": "3",
          "SB": "1",
          "BB": "1",
          "K": "10",
          "TB": "10",
          "AVG": ".182",
          "OPS": ".427",
          "APP": "4",
          "IP": "16.0",
          "ER": "1",
          "P_HR": "0",
          "P_K": "15",
          "P_TB": "15",
          "ERA": "0.56",
          "K/9": "8.44",
          "H/9": "5.63",
          "BB/9": "1.13",
          "QS": "2"
        }
      },
      "team2": {
        "team": "WAR",
        "name": "Weekend Warriors",
        "score": "14",
        "categories": {
          "H/AB": "9/43",
          "R": "5",
          "H": "9",
          "HR": "1",
          "RBI": "4",
          "SB": "0",
          "BB": "5",
          "K": "7",
          "TB": "14",
          "AVG": ".209",
          "OPS": ".617",
          "APP": "6",
          "IP": "16.2",
          "ER": "4",
          "P_HR": "1",
          "P_K": "21",
          "P_TB": "9",
          "ERA": "2.16",
          "K/9": "11.34",
          "H/9": "3.24",
          "BB/9": "3.24",
          "QS": "2"
        }
      }
    }
  ]
}