[
  {
    "player_key": "458.p.9045",
    "player_id": "9045",
    "name": "Mart\u00edn Maldonado",
    "first_name": "Mart\u00edn",
    "last_name": "Maldonado",
    "position": "C",
    "eligible_positions": [],
    "team": "SD",
    "team_full": "San Diego Padres",
    "status": "NA",
    "ownership_type": "freeagents",
    "owned_by": null,
    "percent_owned": 0,
    "stats": {
      "stat_60": "30/147",
      "stat_7": 11,
      "stat_8": 30,
      "stat_12": 4,
      "stat_13": 12,
      "stat_16": 0,
      "stat_18": 8,
      "stat_21": 57,
      "stat_23": 48,
      "stat_3": 0.204,
      "stat_55": 0.572
    }
  },
  {
    "player_key": "458.p.9096",
    "player_id": "9096",
    "name": "Travis d'Arnaud",
    "first_name": "Travis",
    "last_name": "d'Arnaud",
    "position": "C",
    "eligible_positions": [],
    "team": "LAA",
    "team_full": "Los Angeles Angels",
    "status": "DTD",
    "ownership_type": "freeagents",
    "owned_by": null,
    "percent_owned": 1,
    "stats": {
      "stat_60": "42/213",
      "stat_7": 16,
      "stat_8": 42,
      "stat_12": 6,
      "stat_13": 21,
      "stat_16": 0,
      "stat_18": 13,
      "stat_21": 74,
      "stat_23": 73,
      "stat_3": 0.197,
      "stat_55": 0.598
    }
  },
  {
    "player_key": "458.p.9097",
    "player_id": "9097",
    "name": "Gary S\u00e1nchez",
    "first_name": "Gary",
    "last_name": "S\u00e1nchez",
    "position": "C",
    "eligible_positions": [],
    "team": "BAL",
    "team_full": "Baltimore Orioles",
    "status": "NA",
    "ownership_type": "freeagents",
    "owned_by": null,
    "percent_owned": 2,
    "stats": {
      "stat_60": "21/91",
      "stat_7": 13,
      "stat_8": 21,
      "stat_12": 5,
      "stat_13": 24,
      "stat_16": 0,
      "stat_18": 4,
      "stat_21": 27,
      "stat_23": 38,
      "stat_3": 0.231,
      "stat_55": 0.715
    }
  },
  {
    "player_key": "458.p.9180",
    "player_id": "9180",
    "name": "Sandy Le\u00f3n",
    "first_name": "Sandy",
    "last_name": "Le\u00f3n",
    "position": "C",
    "eligible_positions": [],
    "team": "ATL",
    "team_full": "Atlanta Braves",
    "status": "NA",
    "ownership_type": "freeagents",
    "owned_by": null,
    "percent_owned": 0,
    "stats": {
      "stat_60": "1/12",
      "stat_7": 1,
      "stat_8": 1,
      "stat_12": 1,
      "stat_13": 3,
      "stat_16": 0,
      "stat_18": 0,
      "stat_21": 4,
      "stat_23": 4,
      "stat_3": 0.083,
      "stat_55": 0.416
    }
  },
  {
    "player_key": "458.p.9265",
    "player_id": "9265",
    "name": "Rob Brantly",
    "first_name": "Rob",
    "last_name": "Brantly",
    "position": "C",
    "eligible_positions": [],
    "team": "MIA",
    "team_full": "Miami Marlins",
    "status": "NA",
    "ownership_type": "freeagents",
    "owned_by": null,
    "percent_owned": 0,
    "stats": {
      "stat_60": "3/7",
      "stat_7": 0,
      "stat_8": 3,
      "stat_12": 0,
      "stat_13": 1,
      "stat_16": 0,
      "stat_18": 0,
      "stat_21": 1,
      "stat_23": 3,
      "stat_3": 0.429,
      "stat_55": 0.858
    }
  },
  {
    "player_key": "458.p.9336",
    "player_id": "9336",
    "name": "Austin Hedges",
    "first_name": "Austin",
    "last_name": "Hedges",
    "position": "C",
    "eligible_positions": [],
    "team": "CLE",
    "team_full": "Cleveland Guardians",
    "status": "",
    "ownership_type": "freeagents",
    "owned_by": null,
    "percent_owned": 0,
    "stats": {
      "stat_60": "25/155",
      "stat_7": 13,
      "stat_8": 25,
      "stat_12": 5,
      "stat_13": 10,
      "stat_16": 1,
      "stat_18": 18,
      "stat_21": 43,
      "stat_23": 43,
      "stat_3": 0.161,
      "stat_55": 0.527
    }
  },
  {
    "player_key": "458.p.9570",
    "player_id": "9570",
    "name": "Tom Murphy",
    "first_name": "Tom",
    "last_name": "Murphy",
    "position": "C",
    "eligible_positions": [],
    "team": "SF",
    "team_full": "San Francisco Giants",
    "status": "IL60",
    "ownership_type": "freeagents",
    "owned_by": null,
    "percent_owned": 0,
    "stats": {
      "stat_60": "-/-",
      "stat_7": "-",
      "stat_8": "-",
      "stat_12": "-",
      "stat_13": "-",
      "stat_16": "-",
      "stat_18": "-",
      "stat_21": "-",
      "stat_23": "-",
      "stat_3": "-",
      "stat_55": "-"
    }
  },
  {
    "player_key": "458.p.9615",
    "player_id": "9615",
    "name": "Reese McGuire",
    "first_name": "Reese",
    "last_name": "McGuire",
    "position": "C",
    "eligible_positions": [],
    "team": "CHC",
    "team_full": "Chicago Cubs",
    "status": "NA",
    "ownership_type": "freeagents",
    "owned_by": null,
    "percent_owned": 0,
    "stats": {
      "stat_60": "30/133",
      "stat_7": 17,
      "stat_8": 30,
      "stat_12": 9,
      "stat_13": 24,
      "stat_16": 0,
      "stat_18": 4,
      "stat_21": 27,
      "stat_23": 59,
      "stat_3": 0.226,
      "stat_55": 0.689
    }
  },
  {
    "player_key": "458.p.9631",
    "player_id": "9631",
    "name": "Jorge Alfaro",
    "first_name": "Jorge",
    "last_name": "Alfaro",
    "position": "C",
    "eligible_positions": [],
    "team": "WSH",
    "team_full": "Washington Nationals",
    "status": "NA",
    "ownership_type": "freeagents",
    "owned_by": null,
    "percent_owned": 0,
    "stats": {
      "stat_60": "10/39",
      "stat_7": 3,
      "stat_8": 10,
      "stat_12": 0,
      "stat_13": 3,
      "stat_16": 1,
      "stat_18": 0,
      "stat_21": 14,
      "stat_23": 12,
      "stat_3": 0.256,
      "stat_55": 0.564
    }
  },
  {
    "player_key": "458.p.9664",
    "player_id": "9664",
    "name": "Tucker Barnhart",
    "first_name": "Tucker",
    "last_name": "Barnhart",
    "position": "C",
    "eligible_positions": [],
    "team": "TEX",
    "team_full": "Texas Rangers",
    "status": "NA",
    "ownership_type": "freeagents",
    "owned_by": null,
    "percent_owned": 0,
    "stats": {
      "stat_60": "3/13",
      "stat_7": 0,
      "stat_8": 3,
      "stat_12": 0,
      "stat_13": 0,
      "stat_16": 0,
      "stat_18": 1,
      "stat_21": 4,
      "stat_23": 3,
      "stat_3": 0.231,
      "stat_55": 0.564
    }
  },
  {
    "player_key": "458.p.9718",
    "player_id": "9718",
    "name": "J.T. Realmuto",
    "first_name": "J.T.",
    "last_name": "Realmuto",
    "position": "C",
    "eligible_positions": [],
    "team": "PHI",
    "team_full": "Philadelphia Phillies",
    "status": "NA",
    "ownership_type": "team",
    "owned_by": "458.l.15505.t.2",
    "percent_owned": 77,
    "stats": {
      "stat_60": "129/502",
      "stat_7": 57,
      "stat_8": 129,
      "stat_12": 12,
      "stat_13": 52,
      "stat_16": 8,
      "stat_18": 35,
      "stat_21": 129,
      "stat_23": 193,
      "stat_3": 0.257,
      "stat_55": 0.699
    }
  },
  {
    "player_key": "458.p.9762",
    "player_id": "9762",
    "name": "Christian V\u00e1zquez",
    "first_name": "Christian",
    "last_name": "V\u00e1zquez",
    "position": "C",
    "eligible_positions": [],
    "team": "MIN",
    "team_full": "Minnesota Twins",
    "status": "NA",
    "ownership_type": "freeagents",
    "owned_by": null,
    "percent_owned": 0,
    "stats": {
      "stat_60": "36/190",
      "stat_7": 14,
      "stat_8": 36,
      "stat_12": 3,
      "stat_13": 14,
      "stat_16": 1,
      "stat_18": 18,
      "stat_21": 35,
      "stat_23": 52,
      "stat_3": 0.189,
      "stat_55": 0.545
    }
  },
  {
    "player_key": "458.p.9818",
    "player_id": "9818",
    "name": "James McCann",
    "first_name": "James",
    "last_name": "McCann",
    "position": "C",
    "eligible_positions": [],
    "team": "AZ",
    "team_full": "Arizona Diamondbacks",
    "status": "",
    "ownership_type": "freeagents",
    "owned_by": null,
    "percent_owned": 0,
    "stats": {
      "stat_60": "32/123",
      "stat_7": 18,
      "stat_8": 32,
      "stat_12": 5,
      "stat_13": 17,
      "stat_16": 0,
      "stat_18": 8,
      "stat_21": 33,
      "stat_23": 53,
      "stat_3": 0.26,
      "stat_55": 0.755
    }
  },
  {
    "player_key": "458.p.9885",
    "player_id": "9885",
    "name": "Alex Jackson",
    "first_name": "Alex",
    "last_name": "Jackson",
    "position": "C",
    "eligible_positions": [],
    "team": "MIN",
    "team_full": "Minnesota Twins",
    "status": "",
    "ownership_type": "freeagents",
    "owned_by": null,
    "percent_owned": 0,
    "stats": {
      "stat_60": "20/91",
      "stat_7": 17,
      "stat_8": 20,
      "stat_12": 5,
      "stat_13": 8,
      "stat_16": 0,
      "stat_18": 5,
      "stat_21": 37,
      "stat_23": 43,
      "stat_3": 0.22,
      "stat_55": 0.763
    }
  },
  {
    "player_key": "458.p.9971",
    "player_id": "9971",
    "name": "Austin Barnes",
    "first_name": "Austin",
    "last_name": "Barnes",
    "position": "C",
    "eligible_positions": [],
    "team": "LAD",
    "team_full": "Los Angeles Dodgers",
    "status": "NA",
    "ownership_type": "freeagents",
    "owned_by": null,
    "percent_owned": 0,
    "stats": {
      "stat_60": "9/42",
      "stat_7": 4,
      "stat_8": 9,
      "stat_12": 0,
      "stat_13": 2,
      "stat_16": 0,
      "stat_18": 1,
      "stat_21": 14,
      "stat_23": 12,
      "stat_3": 0.214,
      "stat_55": 0.519
    }
  },
  {
    "player_key": "458.p.10068",
    "player_id": "10068",
    "name": "Luke Maile",
    "first_name": "Luke",
    "last_name": "Maile",
    "position": "C",
    "eligible_positions": [],
    "team": "KC",
    "team_full": "Kansas City Royals",
    "status": "NA",
    "ownership_type": "freeagents",
    "owned_by": null,
    "percent_owned": 0,
    "stats": {
      "stat_60": "11/45",
      "stat_7": 6,
      "stat_8": 11,
      "stat_12": 1,
      "stat_13": 6,
      "stat_16": 1,
      "stat_18": 7,
      "stat_21": 16,
      "stat_23": 16,
      "stat_3": 0.244,
      "stat_55": 0.702
    }
  },
  {
    "player_key": "458.p.10076",
    "player_id": "10076",
    "name": "Elias D\u00edaz",
    "first_name": "Elias",
    "last_name": "D\u00edaz",
    "position": "C",
    "eligible_positions": [],
    "team": "SD",
    "team_full": "San Diego Padres",
    "status": "NA",
    "ownership_type": "freeagents",
    "owned_by": null,
    "percent_owned": 1,
    "stats": {
      "stat_60": "52/255",
      "stat_7": 34,
      "stat_8": 52,
      "stat_12": 9,
      "stat_13": 29,
      "stat_16": 0,
      "stat_18": 21,
      "stat_21": 74,
      "stat_23": 86,
      "stat_3": 0.204,
      "stat_55": 0.607
    }
  },
  {
    "player_key": "458.p.10318",
    "player_id": "10318",
    "name": "Jacob Stallings",
    "first_name": "Jacob",
    "last_name": "Stallings",
    "position": "C",
    "eligible_positions": [],
    "team": "BAL",
    "team_full": "Baltimore Orioles",
    "status": "NA",
    "ownership_type": "freeagents",
    "owned_by": null,
    "percent_owned": 0,
    "stats": {
      "stat_60": "16/119",
      "stat_7": 5,
      "stat_8": 16,
      "stat_12": 0,
      "stat_13": 9,
      "stat_16": 0,
      "stat_18": 6,
      "stat_21": 40,
      "stat_23": 20,
      "stat_3": 0.134,
      "stat_55": 0.363
    }
  },
  {
    "player_key": "458.p.10337",
    "player_id": "10337",
    "name": "Omar Narv\u00e1ez",
    "first_name": "Omar",
    "last_name": "Narv\u00e1ez",
    "position": "C",
    "eligible_positions": [],
    "team": "TEX",
    "team_full": "Texas Rangers",
    "status": "NA",
    "ownership_type": "freeagents",
    "owned_by": null,
    "percent_owned": 0,
    "stats": {
      "stat_60": "2/7",
      "stat_7": 1,
      "stat_8": 2,
      "stat_12": 0,
      "stat_13": 3,
      "stat_16": 0,
      "stat_18": 2,
      "stat_21": 1,
      "stat_23": 2,
      "stat_3": 0.286,
      "stat_55": 0.686
    }
  },
  {
    "player_key": "458.p.10395",
    "player_id": "10395",
    "name": "Carson Kelly",
    "first_name": "Carson",
    "last_name": "Kelly",
    "position": "C",
    "eligible_positions": [],
    "team": "CHC",
    "team_full": "Chicago Cubs",
    "status": "",
    "ownership_type": "freeagents",
    "owned_by": null,
    "percent_owned": 21,
    "stats": {
      "stat_60": "92/369",
      "stat_7": 48,
      "stat_8": 92,
      "stat_12": 17,
      "stat_13": 50,
      "stat_16": 2,
      "stat_18": 45,
      "stat_21": 80,
      "stat_23": 158,
      "stat_3": 0.249,
      "stat_55": 0.761
    }
  },
  {
    "player_key": "458.p.10456",
    "player_id": "10456",
    "name": "Tyler Stephenson",
    "first_name": "Tyler",
    "last_name": "Stephenson",
    "position": "C",
    "eligible_positions": [],
    "team": "CIN",
    "team_full": "Cincinnati Reds",
    "status": "",
    "ownership_type": "freeagents",
    "owned_by": null,
    "percent_owned": 23,
    "stats": {
      "stat_60": "69/299",
      "stat_7": 40,
      "stat_8": 69,
      "stat_12": 13,
      "stat_13": 50,
      "stat_16": 0,
      "stat_18": 37,
      "stat_21": 116,
      "stat_23": 126,
      "stat_3": 0.231,
      "stat_55": 0.737
    }
  },
  {
    "player_key": "458.p.10478",
    "player_id": "10478",
    "name": "Garrett Stubbs",
    "first_name": "Garrett",
    "last_name": "Stubbs",
    "position": "C",
    "eligible_positions": [],
    "team": "PHI",
    "team_full": "Philadelphia Phillies",
    "status": "",
    "ownership_type": "freeagents",
    "owned_by": null,
    "percent_owned": 0,
    "stats": {
      "stat_60": "0/1",
      "stat_7": 2,
      "stat_8": 0,
      "stat_12": 0,
      "stat_13": 0,
      "stat_16": 0,
      "stat_18": 0,
      "stat_21": 0,
      "stat_23": 0,
      "stat_3": 0.0,
      "stat_55": 0.0
    }
  },
  {
    "player_key": "458.p.10497",
    "player_id": "10497",
    "name": "Matt Thaiss",
    "first_name": "Matt",
    "last_name": "Thaiss",
    "position": "C",
    "eligible_positions": [],
    "team": "TB",
    "team_full": "Tampa Bay Rays",
    "status": "NA",
    "ownership_type": "freeagents",
    "owned_by": null,
    "percent_owned": 0,
    "stats": {
      "stat_60": "34/156",
      "stat_7": 16,
      "stat_8": 34,
      "stat_12": 1,
      "stat_13": 16,
      "stat_16": 1,
      "stat_18": 29,
      "stat_21": 46,
      "stat_23": 45,
      "stat_3": 0.218,
      "stat_55": 0.637
    }
  },
  {
    "player_key": "458.p.10533",
    "player_id": "10533",
    "name": "Ben Rortvedt",
    "first_name": "Ben",
    "last_name": "Rortvedt",
    "position": "C",
    "eligible_positions": [],
    "team": "CIN",
    "team_full": "Cincinnati Reds",
    "status": "",
    "ownership_type": "freeagents",
    "owned_by": null,
    "percent_owned": 0,
    "stats": {
      "stat_60": "17/112",
      "stat_7": 9,
      "stat_8": 17,
      "stat_12": 1,
      "stat_13": 10,
      "stat_16": 0,
      "stat_18": 11,
      "stat_21": 23,
      "stat_23": 23,
      "stat_3": 0.152,
      "stat_55": 0.445
    }
  },
  {
    "player_key": "458.p.10578",
    "player_id": "10578",
    "name": "Aramis Garcia",
    "first_name": "Aramis",
    "last_name": "Garcia",
    "position": "C",
    "eligible_positions": [],
    "team": "AZ",
    "team_full": "Arizona Diamondbacks",
    "status": "NA",
    "ownership_type": "freeagents",
    "owned_by": null,
    "percent_owned": 0,
    "stats": {
      "stat_60": "0/4",
      "stat_7": 0,
      "stat_8": 0,
      "stat_12": 0,
      "stat_13": 0,
      "stat_16": 0,
      "stat_18": 0,
      "stat_21": 3,
      "stat_23": 0,
      "stat_3": 0.0,
      "stat_55": 0.0
    }
  },
  {
    "player_key": "458.p.10642",
    "player_id": "10642",
    "name": "Will Smith",
    "first_name": "Will",
    "last_name": "Smith",
    "position": "C",
    "eligible_positions": [],
    "team": "LAD",
    "team_full": "Los Angeles Dodgers",
    "status": "",
    "ownership_type": "team",
    "owned_by": "458.l.15505.t.5",
    "percent_owned": 85,
    "stats": {
      "stat_60": "107/362",
      "stat_7": 64,
      "stat_8": 107,
      "stat_12": 17,
      "stat_13": 61,
      "stat_16": 2,
      "stat_18": 64,
      "stat_21": 89,
      "stat_23": 180,
      "stat_3": 0.296,
      "stat_55": 0.901
    }
  },
  {
    "player_key": "458.p.10650",
    "player_id": "10650",
    "name": "Dom Nu\u00f1ez",
    "first_name": "Dom",
    "last_name": "Nu\u00f1ez",
    "position": "C",
    "eligible_positions": [],
    "team": "CLE",
    "team_full": "Cleveland Guardians",
    "status": "NA",
    "ownership_type": "freeagents",
    "owned_by": null,
    "percent_owned": 0,
    "stats": {
      "stat_60": "2/7",
      "stat_7": 2,
      "stat_8": 2,
      "stat_12": 0,
      "stat_13": 0,
      "stat_16": 0,
      "stat_18": 0,
      "stat_21": 4,
      "stat_23": 2,
      "stat_3": 0.286,
      "stat_55": 0.572
    }
  },
  {
    "player_key": "458.p.10669",
    "player_id": "10669",
    "name": "Luis Torrens",
    "first_name": "Luis",
    "last_name": "Torrens",
    "position": "C",
    "eligible_positions": [],
    "team": "NYM",
    "team_full": "New York Mets",
    "status": "",
    "ownership_type": "freeagents",
    "owned_by": null,
    "percent_owned": 1,
    "stats": {
      "stat_60": "59/261",
      "stat_7": 20,
      "stat_8": 59,
      "stat_12": 5,
      "stat_13": 29,
      "stat_16": 1,
      "stat_18": 19,
      "stat_21": 56,
      "stat_23": 90,
      "stat_3": 0.226,
      "stat_55": 0.629
    }
  },
  {
    "player_key": "458.p.10678",
    "player_id": "10678",
    "name": "Kyle Higashioka",
    "first_name": "Kyle",
    "last_name": "Higashioka",
    "position": "C",
    "eligible_positions": [],
    "team": "TEX",
    "team_full": "Texas Rangers",
    "status": "",
    "ownership_type": "freeagents",
    "owned_by": null,
    "percent_owned": 2,
    "stats": {
      "stat_60": "73/303",
      "stat_7": 33,
      "stat_8": 73,
      "stat_12": 11,
      "stat_13": 47,
      "stat_16": 3,
      "stat_18": 20,
      "stat_21": 72,
      "stat_23": 122,
      "stat_3": 0.241,
      "stat_55": 0.694
    }
  },
  {
    "player_key": "458.p.10789",
    "player_id": "10789",
    "name": "Mitch Garver",
    "first_name": "Mitch",
    "last_name": "Garver",
    "position": "C",
    "eligible_positions": [],
    "team": "SEA",
    "team_full": "Seattle Mariners",
    "status": "NA",
    "ownership_type": "freeagents",
    "owned_by": null,
    "percent_owned": 0,
    "stats": {
      "stat_60": "53/254",
      "stat_7": 29,
      "stat_8": 53,
      "stat_12": 9,
      "stat_13": 30,
      "stat_16": 3,
      "stat_18": 30,
      "stat_21": 80,
      "stat_23": 87,
      "stat_3": 0.209,
      "stat_55": 0.64
    }
  },
  {
    "player_key": "458.p.10799",
    "player_id": "10799",
    "name": "Chad Wallach",
    "first_name": "Chad",
    "last_name": "Wallach",
    "position": "C",
    "eligible_positions": [],
    "team": "LAA",
    "team_full": "Los Angeles Angels",
    "status": "NA",
    "ownership_type": "freeagents",
    "owned_by": null,
    "percent_owned": 0,
    "stats": {
      "stat_60": "0/0",
      "stat_7": 0,
      "stat_8": 0,
      "stat_12": 0,
      "stat_13": 0,
      "stat_16": 0,
      "stat_18": 0,
      "stat_21": 0,
      "stat_23": 0,
      "stat_3": "-",
      "stat_55": "-"
    }
  },
  {
    "player_key": "458.p.10829",
    "player_id": "10829",
    "name": "Tom\u00e1s Nido",
    "first_name": "Tom\u00e1s",
    "last_name": "Nido",
    "position": "C",
    "eligible_positions": [],
    "team": "DET",
    "team_full": "Detroit Tigers",
    "status": "NA",
    "ownership_type": "freeagents",
    "owned_by": null,
    "percent_owned": 0,
    "stats": {
      "stat_60": "12/35",
      "stat_7": 4,
      "stat_8": 12,
      "stat_12": 0,
      "stat_13": 2,
      "stat_16": 0,
      "stat_18": 0,
      "stat_21": 10,
      "stat_23": 12,
      "stat_3": 0.343,
      "stat_55": 0.704
    }
  },
  {
    "player_key": "458.p.10899",
    "player_id": "10899",
    "name": "Keibert Ruiz",
    "first_name": "Keibert",
    "last_name": "Ruiz",
    "position": "C",
    "eligible_positions": [],
    "team": "WSH",
    "team_full": "Washington Nationals",
    "status": "DTD",
    "ownership_type": "freeagents",
    "owned_by": null,
    "percent_owned": 9,
    "stats": {
      "stat_60": "63/255",
      "stat_7": 19,
      "stat_8": 63,
      "stat_12": 2,
      "stat_13": 25,
      "stat_16": 0,
      "stat_18": 8,
      "stat_21": 26,
      "stat_23": 81,
      "stat_3": 0.247,
      "stat_55": 0.595
    }
  },
  {
    "player_key": "458.p.10900",
    "player_id": "10900",
    "name": "Jake Rogers",
    "first_name": "Jake",
    "last_name": "Rogers",
    "position": "C",
    "eligible_positions": [],
    "team": "DET",
    "team_full": "Detroit Tigers",
    "status": "",
    "ownership_type": "freeagents",
    "owned_by": null,
    "percent_owned": 0,
    "stats": {
      "stat_60": "23/123",
      "stat_7": 14,
      "stat_8": 23,
      "stat_12": 3,
      "stat_13": 19,
      "stat_16": 0,
      "stat_18": 15,
      "stat_21": 39,
      "stat_23": 41,
      "stat_3": 0.187,
      "stat_55": 0.61
    }
  },
  {
    "player_key": "458.p.10929",
    "player_id": "10929",
    "name": "Sean Murphy",
    "first_name": "Sean",
    "last_name": "Murphy",
    "position": "C",
    "eligible_positions": [],
    "team": "ATL",
    "team_full": "Atlanta Braves",
    "status": "DTD",
    "ownership_type": "freeagents",
    "owned_by": null,
    "percent_owned": 11,
    "stats": {
      "stat_60": "58/291",
      "stat_7": 34,
      "stat_8": 58,
      "stat_12": 16,
      "stat_13": 45,
      "stat_16": 0,
      "stat_18": 35,
      "stat_21": 105,
      "stat_23": 119,
      "stat_3": 0.199,
      "stat_55": 0.709
    }
  },
  {
    "player_key": "458.p.10959",
    "player_id": "10959",
    "name": "Danny Jansen",
    "first_name": "Danny",
    "last_name": "Jansen",
    "position": "C",
    "eligible_positions": [],
    "team": "TEX",
    "team_full": "Texas Rangers",
    "status": "",
    "ownership_type": "freeagents",
    "owned_by": null,
    "percent_owned": 2,
    "stats": {
      "stat_60": "62/288",
      "stat_7": 38,
      "stat_8": 62,
      "stat_12": 14,
      "stat_13": 36,
      "stat_16": 0,
      "stat_18": 42,
      "stat_21": 86,
      "stat_23": 115,
      "stat_3": 0.215,
      "stat_55": 0.72
    }
  },
  {
    "player_key": "458.p.11033",
    "player_id": "11033",
    "name": "Austin Wynns",
    "first_name": "Austin",
    "last_name": "Wynns",
    "position": "C",
    "eligible_positions": [],
    "team": "ATH",
    "team_full": " Athletics",
    "status": "DTD",
    "ownership_type": "freeagents",
    "owned_by": null,
    "percent_owned": 0,
    "stats": {
      "stat_60": "30/103",
      "stat_7": 13,
      "stat_8": 30,
      "stat_12": 6,
      "stat_13": 21,
      "stat_16": 0,
      "stat_18": 5,
      "stat_21": 32,
      "stat_23": 56,
      "stat_3": 0.291,
      "stat_55": 0.865
    }
  },
  {
    "player_key": "458.p.11045",
    "player_id": "11045",
    "name": "Jose Trevino",
    "first_name": "Jose",
    "last_name": "Trevino",
    "position": "C",
    "eligible_positions": [],
    "team": "CIN",
    "team_full": "Cincinnati Reds",
    "status": "",
    "ownership_type": "freeagents",
    "owned_by": null,
    "percent_owned": 1,
    "stats": {
      "stat_60": "67/282",
      "stat_7": 30,
      "stat_8": 67,
      "stat_12": 4,
      "stat_13": 22,
      "stat_16": 0,
      "stat_18": 15,
      "stat_21": 39,
      "stat_23": 99,
      "stat_3": 0.238,
      "stat_55": 0.623
    }
  },
  {
    "player_key": "458.p.11075",
    "player_id": "11075",
    "name": "Miguel Amaya",
    "first_name": "Miguel",
    "last_name": "Amaya",
    "position": "C",
    "eligible_positions": [],
    "team": "CHC",
    "team_full": "Chicago Cubs",
    "status": "",
    "ownership_type": "freeagents",
    "owned_by": null,
    "percent_owned": 1,
    "stats": {
      "stat_60": "27/96",
      "stat_7": 14,
      "stat_8": 27,
      "stat_12": 4,
      "stat_13": 25,
      "stat_16": 0,
      "stat_18": 4,
      "stat_21": 22,
      "stat_23": 48,
      "stat_3": 0.281,
      "stat_55": 0.814
    }
  },
  {
    "player_key": "458.p.11077",
    "player_id": "11077",
    "name": "Eric Haase",
    "first_name": "Eric",
    "last_name": "Haase",
    "position": "C",
    "eligible_positions": [],
    "team": "MIL",
    "team_full": "Milwaukee Brewers",
    "status": "NA",
    "ownership_type": "freeagents",
    "owned_by": null,
    "percent_owned": 0,
    "stats": {
      "stat_60": "16/70",
      "stat_7": 11,
      "stat_8": 16,
      "stat_12": 2,
      "stat_13": 9,
      "stat_16": 0,
      "stat_18": 4,
      "stat_21": 31,
      "stat_23": 25,
      "stat_3": 0.229,
      "stat_55": 0.646
    }
  },
  {
    "player_key": "458.p.11097",
    "player_id": "11097",
    "name": "Joey Bart",
    "first_name": "Joey",
    "last_name": "Bart",
    "position": "C",
    "eligible_positions": [],
    "team": "PIT",
    "team_full": "Pittsburgh Pirates",
    "status": "",
    "ownership_type": "freeagents",
    "owned_by": null,
    "percent_owned": 4,
    "stats": {
      "stat_60": "71/285",
      "stat_7": 21,
      "stat_8": 71,
      "stat_12": 4,
      "stat_13": 30,
      "stat_16": 1,
      "stat_18": 40,
      "stat_21": 93,
      "stat_23": 97,
      "stat_3": 0.249,
      "stat_55": 0.695
    }
  },
  {
    "player_key": "458.p.11268",
    "player_id": "11268",
    "name": "William Contreras",
    "first_name": "William",
    "last_name": "Contreras",
    "position": "C",
    "eligible_positions": [],
    "team": "MIL",
    "team_full": "Milwaukee Brewers",
    "status": "",
    "ownership_type": "team",
    "owned_by": "458.l.15505.t.12",
    "percent_owned": 95,
    "stats": {
      "stat_60": "147/566",
      "stat_7": 89,
      "stat_8": 147,
      "stat_12": 17,
      "stat_13": 76,
      "stat_16": 6,
      "stat_18": 84,
      "stat_21": 120,
      "stat_23": 226,
      "stat_3": 0.26,
      "stat_55": 0.754
    }
  },
  {
    "player_key": "458.p.11296",
    "player_id": "11296",
    "name": "Bo Naylor",
    "first_name": "Bo",
    "last_name": "Naylor",
    "position": "C",
    "eligible_positions": [],
    "team": "CLE",
    "team_full": "Cleveland Guardians",
    "status": "",
    "ownership_type": "freeagents",
    "owned_by": null,
    "percent_owned": 8,
    "stats": {
      "stat_60": "70/359",
      "stat_7": 46,
      "stat_8": 70,
      "stat_12": 14,
      "stat_13": 47,
      "stat_16": 1,
      "stat_18": 45,
      "stat_21": 99,
      "stat_23": 136,
      "stat_3": 0.195,
      "stat_55": 0.661
    }
  },
  {
    "player_key": "458.p.11329",
    "player_id": "11329",
    "name": "Diego Cartaya",
    "first_name": "Diego",
    "last_name": "Cartaya",
    "position": "C",
    "eligible_positions": [],
    "team": "MIN",
    "team_full": "Minnesota Twins",
    "status": "NA",
    "ownership_type": "freeagents",
    "owned_by": null,
    "percent_owned": 0,
    "stats": {
      "stat_60": "-/-",
      "stat_7": "-",
      "stat_8": "-",
      "stat_12": "-",
      "stat_13": "-",
      "stat_16": "-",
      "stat_18": "-",
      "stat_21": "-",
      "stat_23": "-",
      "stat_3": "-",
      "stat_55": "-"
    }
  },
  {
    "player_key": "458.p.11334",
    "player_id": "11334",
    "name": "Will Banfield",
    "first_name": "Will",
    "last_name": "Banfield",
    "position": "C",
    "eligible_positions": [],
    "team": "CIN",
    "team_full": "Cincinnati Reds",
    "status": "NA",
    "ownership_type": "freeagents",
    "owned_by": null,
    "percent_owned": 0,
    "stats": {
      "stat_60": "1/10",
      "stat_7": 0,
      "stat_8": 1,
      "stat_12": 0,
      "stat_13": 0,
      "stat_16": 0,
      "stat_18": 0,
      "stat_21": 6,
      "stat_23": 1,
      "stat_3": 0.1,
      "stat_55": 0.2
    }
  },
  {
    "player_key": "458.p.11349",
    "player_id": "11349",
    "name": "Francisco Alvarez",
    "first_name": "Francisco",
    "last_name": "Alvarez",
    "position": "C",
    "eligible_positions": [],
    "team": "NYM",
    "team_full": "New York Mets",
    "status": "DTD",
    "ownership_type": "team",
    "owned_by": "458.l.15505.t.3",
    "percent_owned": 19,
    "stats": {
      "stat_60": "63/246",
      "stat_7": 32,
      "stat_8": 63,
      "stat_12": 11,
      "stat_13": 32,
      "stat_16": 0,
      "stat_18": 27,
      "stat_21": 73,
      "stat_23": 110,
      "stat_3": 0.256,
      "stat_55": 0.786
    }
  },
  {
    "player_key": "458.p.11392",
    "player_id": "11392",
    "name": "Andrew Knizner",
    "first_name": "Andrew",
    "last_name": "Knizner",
    "position": "C",
    "eligible_positions": [],
    "team": "SEA",
    "team_full": "Seattle Mariners",
    "status": "",
    "ownership_type": "freeagents",
    "owned_by": null,
    "percent_owned": 0,
    "stats": {
      "stat_60": "17/77",
      "stat_7": 12,
      "stat_8": 17,
      "stat_12": 1,
      "stat_13": 5,
      "stat_16": 0,
      "stat_18": 7,
      "stat_21": 10,
      "stat_23": 23,
      "stat_3": 0.221,
      "stat_55": 0.598
    }
  },
  {
    "player_key": "458.p.11437",
    "player_id": "11437",
    "name": "Jhonny Pereda",
    "first_name": "Jhonny",
    "last_name": "Pereda",
    "position": "C",
    "eligible_positions": [],
    "team": "MIN",
    "team_full": "Minnesota Twins",
    "status": "",
    "ownership_type": "freeagents",
    "owned_by": null,
    "percent_owned": 0,
    "stats": {
      "stat_60": "17/69",
      "stat_7": 4,
      "stat_8": 17,
      "stat_12": 0,
      "stat_13": 4,
      "stat_16": 0,
      "stat_18": 8,
      "stat_21": 21,
      "stat_23": 23,
      "stat_3": 0.246,
      "stat_55": 0.658
    }
  },
  {
    "player_key": "458.p.11527",
    "player_id": "11527",
    "name": "Luis Campusano",
    "first_name": "Luis",
    "last_name": "Campusano",
    "position": "C",
    "eligible_positions": [],
    "team": "SD",
    "team_full": "San Diego Padres",
    "status": "",
    "ownership_type": "freeagents",
    "owned_by": null,
    "percent_owned": 0,
    "stats": {
      "stat_60": "0/21",
      "stat_7": 0,
      "stat_8": 0,
      "stat_12": 0,
      "stat_13": 0,
      "stat_16": 0,
      "stat_18": 6,
      "stat_21": 11,
      "stat_23": 0,
      "stat_3": 0.0,
      "stat_55": 0.222
    }
  },
  {
    "player_key": "458.p.11531",
    "player_id": "11531",
    "name": "Cal Raleigh",
    "first_name": "Cal",
    "last_name": "Raleigh",
    "position": "C",
    "eligible_positions": [],
    "team": "SEA",
    "team_full": "Seattle Mariners",
    "status": "",
    "ownership_type": "team",
    "owned_by": "458.l.15505.t.1",
    "percent_owned": 99,
    "stats": {
      "stat_60": "147/596",
      "stat_7": 110,
      "stat_8": 147,
      "stat_12": 60,
      "stat_13": 125,
      "stat_16": 14,
      "stat_18": 97,
      "stat_21": 188,
      "stat_23": 351,
      "stat_3": 0.247,
      "stat_55": 0.948
    }
  },
  {
    "player_key": "458.p.11599",
    "player_id": "11599",
    "name": "Austin Nola",
    "first_name": "Austin",
    "last_name": "Nola",
    "position": "C",
    "eligible_positions": [],
    "team": "ATL",
    "team_full": "Atlanta Braves",
    "status": "NA",
    "ownership_type": "freeagents",
    "owned_by": null,
    "percent_owned": 0,
    "stats": {
      "stat_60": "7/38",
      "stat_7": 2,
      "stat_8": 7,
      "stat_12": 0,
      "stat_13": 1,
      "stat_16": 0,
      "stat_18": 2,
      "stat_21": 5,
      "stat_23": 8,
      "stat_3": 0.184,
      "stat_55": 0.436
    }
  },
  {
    "player_key": "458.p.11652",
    "player_id": "11652",
    "name": "Tyler Heineman",
    "first_name": "Tyler",
    "last_name": "Heineman",
    "position": "C",
    "eligible_positions": [],
    "team": "TOR",
    "team_full": "Toronto Blue Jays",
    "status": "",
    "ownership_type": "freeagents",
    "owned_by": null,
    "percent_owned": 0,
    "stats": {
      "stat_60": "43/149",
      "stat_7": 25,
      "stat_8": 43,
      "stat_12": 3,
      "stat_13": 20,
      "stat_16": 2,
      "stat_18": 12,
      "stat_21": 31,
      "stat_23": 62,
      "stat_3": 0.289,
      "stat_55": 0.777
    }
  },
  {
    "player_key": "458.p.11662",
    "player_id": "11662",
    "name": "Jonah Heim",
    "first_name": "Jonah",
    "last_name": "Heim",
    "position": "C",
    "eligible_positions": [],
    "team": "TEX",
    "team_full": "Texas Rangers",
    "status": "NA",
    "ownership_type": "freeagents",
    "owned_by": null,
    "percent_owned": 5,
    "stats": {
      "stat_60": "84/395",
      "stat_7": 38,
      "stat_8": 84,
      "stat_12": 11,
      "stat_13": 43,
      "stat_16": 3,
      "stat_18": 32,
      "stat_21": 88,
      "stat_23": 131,
      "stat_3": 0.213,
      "stat_55": 0.603
    }
  },
  {
    "player_key": "458.p.11676",
    "player_id": "11676",
    "name": "Al\u00ed S\u00e1nchez",
    "first_name": "Al\u00ed",
    "last_name": "S\u00e1nchez",
    "position": "C",
    "eligible_positions": [],
    "team": "NYY",
    "team_full": "New York Yankees",
    "status": "NA",
    "ownership_type": "freeagents",
    "owned_by": null,
    "percent_owned": 0,
    "stats": {
      "stat_60": "5/23",
      "stat_7": 2,
      "stat_8": 5,
      "stat_12": 0,
      "stat_13": 0,
      "stat_16": 0,
      "stat_18": 0,
      "stat_21": 6,
      "stat_23": 7,
      "stat_3": 0.217,
      "stat_55": 0.521
    }
  },
  {
    "player_key": "458.p.11728",
    "player_id": "11728",
    "name": "Shea Langeliers",
    "first_name": "Shea",
    "last_name": "Langeliers",
    "position": "C",
    "eligible_positions": [],
    "team": "ATH",
    "team_full": " Athletics",
    "status": "",
    "ownership_type": "team",
    "owned_by": "458.l.15505.t.6",
    "percent_owned": 90,
    "stats": {
      "stat_60": "133/481",
      "stat_7": 73,
      "stat_8": 133,
      "stat_12": 31,
      "stat_13": 72,
      "stat_16": 7,
      "stat_18": 36,
      "stat_21": 103,
      "stat_23": 258,
      "stat_3": 0.277,
      "stat_55": 0.861
    }
  },
  {
    "player_key": "458.p.11732",
    "player_id": "11732",
    "name": "Adley Rutschman",
    "first_name": "Adley",
    "last_name": "Rutschman",
    "position": "C",
    "eligible_positions": [],
    "team": "BAL",
    "team_full": "Baltimore Orioles",
    "status": "",
    "ownership_type": "team",
    "owned_by": "458.l.15505.t.3",
    "percent_owned": 67,
    "stats": {
      "stat_60": "71/322",
      "stat_7": 37,
      "stat_8": 71,
      "stat_12": 9,
      "stat_13": 29,
      "stat_16": 0,
      "stat_18": 40,
      "stat_21": 57,
      "stat_23": 118,
      "stat_3": 0.22,
      "stat_55": 0.673
    }
  },
  {
    "player_key": "458.p.11767",
    "player_id": "11767",
    "name": "Korey Lee",
    "first_name": "Korey",
    "last_name": "Lee",
    "position": "C",
    "eligible_positions": [],
    "team": "CWS",
    "team_full": "Chicago White Sox",
    "status": "",
    "ownership_type": "freeagents",
    "owned_by": null,
    "percent_owned": 0,
    "stats": {
      "stat_60": "9/35",
      "stat_7": 10,
      "stat_8": 9,
      "stat_12": 1,
      "stat_13": 3,
      "stat_16": 0,
      "stat_18": 4,
      "stat_21": 7,
      "stat_23": 15,
      "stat_3": 0.257,
      "stat_55": 0.762
    }
  },
  {
    "player_key": "458.p.11794",
    "player_id": "11794",
    "name": "Ryan Jeffers",
    "first_name": "Ryan",
    "last_name": "Jeffers",
    "position": "C",
    "eligible_positions": [],
    "team": "MIN",
    "team_full": "Minnesota Twins",
    "status": "",
    "ownership_type": "freeagents",
    "owned_by": null,
    "percent_owned": 14,
    "stats": {
      "stat_60": "108/406",
      "stat_7": 47,
      "stat_8": 108,
      "stat_12": 9,
      "stat_13": 47,
      "stat_16": 1,
      "stat_18": 50,
      "stat_21": 91,
      "stat_23": 161,
      "stat_3": 0.266,
      "stat_55": 0.753
    }
  },
  {
    "player_key": "458.p.11813",
    "player_id": "11813",
    "name": "Rafael March\u00e1n",
    "first_name": "Rafael",
    "last_name": "March\u00e1n",
    "position": "C",
    "eligible_positions": [],
    "team": "PHI",
    "team_full": "Philadelphia Phillies",
    "status": "",
    "ownership_type": "freeagents",
    "owned_by": null,
    "percent_owned": 0,
    "stats": {
      "stat_60": "22/105",
      "stat_7": 9,
      "stat_8": 22,
      "stat_12": 2,
      "stat_13": 13,
      "stat_16": 0,
      "stat_18": 10,
      "stat_21": 17,
      "stat_23": 32,
      "stat_3": 0.21,
      "stat_55": 0.587
    }
  },
  {
    "player_key": "458.p.11836",
    "player_id": "11836",
    "name": "Ivan Herrera",
    "first_name": "Ivan",
    "last_name": "Herrera",
    "position": "C",
    "eligible_positions": [],
    "team": "STL",
    "team_full": "St. Louis Cardinals",
    "status": "DTD",
    "ownership_type": "team",
    "owned_by": "458.l.15505.t.2",
    "percent_owned": 69,
    "stats": {
      "stat_60": "110/388",
      "stat_7": 54,
      "stat_8": 110,
      "stat_12": 19,
      "stat_13": 66,
      "stat_16": 8,
      "stat_18": 43,
      "stat_21": 84,
      "stat_23": 180,
      "stat_3": 0.284,
      "stat_55": 0.837
    }
  },
  {
    "player_key": "458.p.11849",
    "player_id": "11849",
    "name": "Sam Huff",
    "first_name": "Sam",
    "last_name": "Huff",
    "position": "C",
    "eligible_positions": [],
    "team": "SF",
    "team_full": "San Francisco Giants",
    "status": "NA",
    "ownership_type": "freeagents",
    "owned_by": null,
    "percent_owned": 0,
    "stats": {
      "stat_60": "11/53",
      "stat_7": 5,
      "stat_8": 11,
      "stat_12": 2,
      "stat_13": 4,
      "stat_16": 0,
      "stat_18": 4,
      "stat_21": 25,
      "stat_23": 18,
      "stat_3": 0.208,
      "stat_55": 0.599
    }
  },
  {
    "player_key": "458.p.11853",
    "player_id": "11853",
    "name": "Alejandro Kirk",
    "first_name": "Alejandro",
    "last_name": "Kirk",
    "position": "C",
    "eligible_positions": [],
    "team": "TOR",
    "team_full": "Toronto Blue Jays",
    "status": "",
    "ownership_type": "team",
    "owned_by": "458.l.15505.t.3",
    "percent_owned": 40,
    "stats": {
      "stat_60": "127/451",
      "stat_7": 45,
      "stat_8": 127,
      "stat_12": 15,
      "stat_13": 76,
      "stat_16": 1,
      "stat_18": 48,
      "stat_21": 59,
      "stat_23": 190,
      "stat_3": 0.282,
      "stat_55": 0.769
    }
  },
  {
    "player_key": "458.p.11855",
    "player_id": "11855",
    "name": "Gabriel Moreno",
    "first_name": "Gabriel",
    "last_name": "Moreno",
    "position": "C",
    "eligible_positions": [],
    "team": "AZ",
    "team_full": "Arizona Diamondbacks",
    "status": "",
    "ownership_type": "team",
    "owned_by": "458.l.15505.t.7",
    "percent_owned": 34,
    "stats": {
      "stat_60": "79/277",
      "stat_7": 44,
      "stat_8": 79,
      "stat_12": 9,
      "stat_13": 40,
      "stat_16": 2,
      "stat_18": 29,
      "stat_21": 53,
      "stat_23": 120,
      "stat_3": 0.285,
      "stat_55": 0.786
    }
  },
  {
    "player_key": "458.p.11918",
    "player_id": "11918",
    "name": "Brian Navarreto",
    "first_name": "Brian",
    "last_name": "Navarreto",
    "position": "C",
    "eligible_positions": [],
    "team": "MIA",
    "team_full": "Miami Marlins",
    "status": "NA",
    "ownership_type": "freeagents",
    "owned_by": null,
    "percent_owned": 0,
    "stats": {
      "stat_60": "4/14",
      "stat_7": 3,
      "stat_8": 4,
      "stat_12": 1,
      "stat_13": 5,
      "stat_16": 0,
      "stat_18": 0,
      "stat_21": 3,
      "stat_23": 9,
      "stat_3": 0.286,
      "stat_55": 0.91
    }
  },
  {
    "player_key": "458.p.11928",
    "player_id": "11928",
    "name": "Dillon Dingler",
    "first_name": "Dillon",
    "last_name": "Dingler",
    "position": "C",
    "eligible_positions": [],
    "team": "DET",
    "team_full": "Detroit Tigers",
    "status": "",
    "ownership_type": "freeagents",
    "owned_by": null,
    "percent_owned": 15,
    "stats": {
      "stat_60": "121/435",
      "stat_7": 54,
      "stat_8": 121,
      "stat_12": 13,
      "stat_13": 57,
      "stat_16": 0,
      "stat_18": 23,
      "stat_21": 110,
      "stat_23": 185,
      "stat_3": 0.278,
      "stat_55": 0.752
    }
  },
  {
    "player_key": "458.p.11938",
    "player_id": "11938",
    "name": "Sebasti\u00e1n Rivero",
    "first_name": "Sebasti\u00e1n",
    "last_name": "Rivero",
    "position": "C",
    "eligible_positions": [],
    "team": "LAA",
    "team_full": "Los Angeles Angels",
    "status": "NA",
    "ownership_type": "freeagents",
    "owned_by": null,
    "percent_owned": 0,
    "stats": {
      "stat_60": "6/33",
      "stat_7": 4,
      "stat_8": 6,
      "stat_12": 0,
      "stat_13": 2,
      "stat_16": 1,
      "stat_18": 1,
      "stat_21": 9,
      "stat_23": 8,
      "stat_3": 0.182,
      "stat_55": 0.448
    }
  },
  {
    "player_key": "458.p.11997",
    "player_id": "11997",
    "name": "Riley Adams",
    "first_name": "Riley",
    "last_name": "Adams",
    "position": "C",
    "eligible_positions": [],
    "team": "WSH",
    "team_full": "Washington Nationals",
    "status": "",
    "ownership_type": "freeagents",
    "owned_by": null,
    "percent_owned": 0,
    "stats": {
      "stat_60": "49/263",
      "stat_7": 29,
      "stat_8": 49,
      "stat_12": 8,
      "stat_13": 24,
      "stat_16": 1,
      "stat_18": 18,
      "stat_21": 110,
      "stat_23": 81,
      "stat_3": 0.186,
      "stat_55": 0.56
    }
  },
  {
    "player_key": "458.p.12001",
    "player_id": "12001",
    "name": "Kyle McCann",
    "first_name": "Kyle",
    "last_name": "McCann",
    "position": "C",
    "eligible_positions": [],
    "team": "ATH",
    "team_full": " Athletics",
    "status": "NA",
    "ownership_type": "freeagents",
    "owned_by": null,
    "percent_owned": 0,
    "stats": {
      "stat_60": "-/-",
      "stat_7": "-",
      "stat_8": "-",
      "stat_12": "-",
      "stat_13": "-",
      "stat_16": "-",
      "stat_18": "-",
      "stat_21": "-",
      "stat_23": "-",
      "stat_3": "-",
      "stat_55": "-"
    }
  },
  {
    "player_key": "458.p.12009",
    "player_id": "12009",
    "name": "Chadwick Tromp",
    "first_name": "Chadwick",
    "last_name": "Tromp",
    "position": "C",
    "eligible_positions": [],
    "team": "ATL",
    "team_full": "Atlanta Braves",
    "status": "NA",
    "ownership_type": "freeagents",
    "owned_by": null,
    "percent_owned": 0,
    "stats": {
      "stat_60": "3/21",
      "stat_7": 2,
      "stat_8": 3,
      "stat_12": 1,
      "stat_13": 1,
      "stat_16": 0,
      "stat_18": 1,
      "stat_21": 6,
      "stat_23": 7,
      "stat_3": 0.143,
      "stat_55": 0.515
    }
  },
  {
    "player_key": "458.p.12011",
    "player_id": "12011",
    "name": "Logan O'Hoppe",
    "first_name": "Logan",
    "last_name": "O'Hoppe",
    "position": "C",
    "eligible_positions": [],
    "team": "LAA",
    "team_full": "Los Angeles Angels",
    "status": "",
    "ownership_type": "freeagents",
    "owned_by": null,
    "percent_owned": 48,
    "stats": {
      "stat_60": "90/423",
      "stat_7": 35,
      "stat_8": 90,
      "stat_12": 19,
      "stat_13": 43,
      "stat_16": 2,
      "stat_18": 24,
      "stat_21": 139,
      "stat_23": 157,
      "stat_3": 0.213,
      "stat_55": 0.629
    }
  },
  {
    "player_key": "458.p.12013",
    "player_id": "12013",
    "name": "Freddy Fermin",
    "first_name": "Freddy",
    "last_name": "Fermin",
    "position": "C",
    "eligible_positions": [],
    "team": "SD",
    "team_full": "San Diego Padres",
    "status": "",
    "ownership_type": "freeagents",
    "owned_by": null,
    "percent_owned": 1,
    "stats": {
      "stat_60": "80/319",
      "stat_7": 32,
      "stat_8": 80,
      "stat_12": 5,
      "stat_13": 26,
      "stat_16": 1,
      "stat_18": 19,
      "stat_21": 65,
      "stat_23": 108,
      "stat_3": 0.251,
      "stat_55": 0.636
    }
  },
  {
    "player_key": "458.p.12054",
    "player_id": "12054",
    "name": "Patrick Bailey",
    "first_name": "Patrick",
    "last_name": "Bailey",
    "position": "C",
    "eligible_positions": [],
    "team": "SF",
    "team_full": "San Francisco Giants",
    "status": "",
    "ownership_type": "freeagents",
    "owned_by": null,
    "percent_owned": 7,
    "stats": {
      "stat_60": "91/409",
      "stat_7": 47,
      "stat_8": 91,
      "stat_12": 6,
      "stat_13": 55,
      "stat_16": 1,
      "stat_18": 30,
      "stat_21": 133,
      "stat_23": 133,
      "stat_3": 0.222,
      "stat_55": 0.602
    }
  },
  {
    "player_key": "458.p.12058",
    "player_id": "12058",
    "name": "Ren\u00e9 Pinto",
    "first_name": "Ren\u00e9",
    "last_name": "Pinto",
    "position": "C",
    "eligible_positions": [],
    "team": "AZ",
    "team_full": "Arizona Diamondbacks",
    "status": "NA",
    "ownership_type": "freeagents",
    "owned_by": null,
    "percent_owned": 0,
    "stats": {
      "stat_60": "-/-",
      "stat_7": "-",
      "stat_8": "-",
      "stat_12": "-",
      "stat_13": "-",
      "stat_16": "-",
      "stat_18": "-",
      "stat_21": "-",
      "stat_23": "-",
      "stat_3": "-",
      "stat_55": "-"
    }
  },
  {
    "player_key": "458.p.12063",
    "player_id": "12063",
    "name": "Brett Sullivan",
    "first_name": "Brett",
    "last_name": "Sullivan",
    "position": "C",
    "eligible_positions": [],
    "team": "COL",
    "team_full": "Colorado Rockies",
    "status": "NA",
    "ownership_type": "freeagents",
    "owned_by": null,
    "percent_owned": 0,
    "stats": {
      "stat_60": "1/6",
      "stat_7": 1,
      "stat_8": 1,
      "stat_12": 0,
      "stat_13": 2,
      "stat_16": 0,
      "stat_18": 1,
      "stat_21": 3,
      "stat_23": 1,
      "stat_3": 0.167,
      "stat_55": 0.5
    }
  },
  {
    "player_key": "458.p.12066",
    "player_id": "12066",
    "name": "Willie MacIver",
    "first_name": "Willie",
    "last_name": "MacIver",
    "position": "C",
    "eligible_positions": [],
    "team": "TEX",
    "team_full": "Texas Rangers",
    "status": "",
    "ownership_type": "freeagents",
    "owned_by": null,
    "percent_owned": 0,
    "stats": {
      "stat_60": "19/102",
      "stat_7": 7,
      "stat_8": 19,
      "stat_12": 3,
      "stat_13": 9,
      "stat_16": 3,
      "stat_18": 7,
      "stat_21": 27,
      "stat_23": 33,
      "stat_3": 0.186,
      "stat_55": 0.576
    }
  },
  {
    "player_key": "458.p.12088",
    "player_id": "12088",
    "name": "Blake Hunt",
    "first_name": "Blake",
    "last_name": "Hunt",
    "position": "C",
    "eligible_positions": [],
    "team": "SD",
    "team_full": "San Diego Padres",
    "status": "NA",
    "ownership_type": "freeagents",
    "owned_by": null,
    "percent_owned": 0,
    "stats": {
      "stat_60": "-/-",
      "stat_7": "-",
      "stat_8": "-",
      "stat_12": "-",
      "stat_13": "-",
      "stat_16": "-",
      "stat_18": "-",
      "stat_21": "-",
      "stat_23": "-",
      "stat_3": "-",
      "stat_55": "-"
    }
  },
  {
    "player_key": "458.p.12134",
    "player_id": "12134",
    "name": "Drew Romo",
    "first_name": "Drew",
    "last_name": "Romo",
    "position": "C",
    "eligible_positions": [],
    "team": "NYM",
    "team_full": "New York Mets",
    "status": "",
    "ownership_type": "freeagents",
    "owned_by": null,
    "percent_owned": 0,
    "stats": {
      "stat_60": "0/3",
      "stat_7": 0,
      "stat_8": 0,
      "stat_12": 0,
      "stat_13": 0,
      "stat_16": 0,
      "stat_18": 0,
      "stat_21": 3,
      "stat_23": 0,
      "stat_3": 0.0,
      "stat_55": 0.0
    }
  },
  {
    "player_key": "458.p.12161",
    "player_id": "12161",
    "name": "Austin Wells",
    "first_name": "Austin",
    "last_name": "Wells",
    "position": "C",
    "eligible_positions": [],
    "team": "NYY",
    "team_full": "New York Yankees",
    "status": "",
    "ownership_type": "freeagents",
    "owned_by": null,
    "percent_owned": 51,
    "stats": {
      "stat_60": "88/401",
      "stat_7": 51,
      "stat_8": 88,
      "stat_12": 21,
      "stat_13": 71,
      "stat_16": 5,
      "stat_18": 30,
      "stat_21": 118,
      "stat_23": 175,
      "stat_3": 0.219,
      "stat_55": 0.711
    }
  },
  {
    "player_key": "458.p.12250",
    "player_id": "12250",
    "name": "Yohel Pozo",
    "first_name": "Yohel",
    "last_name": "Pozo",
    "position": "C",
    "eligible_positions": [],
    "team": "STL",
    "team_full": "St. Louis Cardinals",
    "status": "",
    "ownership_type": "freeagents",
    "owned_by": null,
    "percent_owned": 0,
    "stats": {
      "stat_60": "37/160",
      "stat_7": 16,
      "stat_8": 37,
      "stat_12": 5,
      "stat_13": 19,
      "stat_16": 0,
      "stat_18": 7,
      "stat_21": 22,
      "stat_23": 60,
      "stat_3": 0.231,
      "stat_55": 0.637
    }
  },
  {
    "player_key": "458.p.12271",
    "player_id": "12271",
    "name": "Nick Fortes",
    "first_name": "Nick",
    "last_name": "Fortes",
    "position": "C",
    "eligible_positions": [],
    "team": "TB",
    "team_full": "Tampa Bay Rays",
    "status": "",
    "ownership_type": "freeagents",
    "owned_by": null,
    "percent_owned": 0,
    "stats": {
      "stat_60": "50/218",
      "stat_7": 19,
      "stat_8": 50,
      "stat_12": 5,
      "stat_13": 21,
      "stat_16": 1,
      "stat_18": 14,
      "stat_21": 47,
      "stat_23": 76,
      "stat_3": 0.229,
      "stat_55": 0.645
    }
  },
  {
    "player_key": "458.p.12292",
    "player_id": "12292",
    "name": "Jose Herrera",
    "first_name": "Jose",
    "last_name": "Herrera",
    "position": "C",
    "eligible_positions": [],
    "team": "TEX",
    "team_full": "Texas Rangers",
    "status": "NA",
    "ownership_type": "freeagents",
    "owned_by": null,
    "percent_owned": 0,
    "stats": {
      "stat_60": "31/166",
      "stat_7": 21,
      "stat_8": 31,
      "stat_12": 2,
      "stat_13": 17,
      "stat_16": 0,
      "stat_18": 23,
      "stat_21": 47,
      "stat_23": 43,
      "stat_3": 0.187,
      "stat_55": 0.544
    }
  },
  {
    "player_key": "458.p.12359",
    "player_id": "12359",
    "name": "Adrian Del Castillo",
    "first_name": "Adrian",
    "last_name": "Del Castillo",
    "position": "C",
    "eligible_positions": [],
    "team": "AZ",
    "team_full": "Arizona Diamondbacks",
    "status": "",
    "ownership_type": "freeagents",
    "owned_by": null,
    "percent_owned": 0,
    "stats": {
      "stat_60": "29/120",
      "stat_7": 9,
      "stat_8": 29,
      "stat_12": 4,
      "stat_13": 17,
      "stat_16": 0,
      "stat_18": 8,
      "stat_21": 47,
      "stat_23": 47,
      "stat_3": 0.242,
      "stat_55": 0.682
    }
  },
  {
    "player_key": "458.p.12451",
    "player_id": "12451",
    "name": "Carter Jensen",
    "first_name": "Carter",
    "last_name": "Jensen",
    "position": "C",
    "eligible_positions": [],
    "team": "KC",
    "team_full": "Kansas City Royals",
    "status": "",
    "ownership_type": "freeagents",
    "owned_by": null,
    "percent_owned": 5,
    "stats": {
      "stat_60": "18/60",
      "stat_7": 12,
      "stat_8": 18,
      "stat_12": 3,
      "stat_13": 13,
      "stat_16": 0,
      "stat_18": 9,
      "stat_21": 12,
      "stat_23": 33,
      "stat_3": 0.3,
      "stat_55": 0.941
    }
  },
  {
    "player_key": "458.p.12457",
    "player_id": "12457",
    "name": "Edgar Quero",
    "first_name": "Edgar",
    "last_name": "Quero",
    "position": "C",
    "eligible_positions": [],
    "team": "CWS",
    "team_full": "Chicago White Sox",
    "status": "",
    "ownership_type": "freeagents",
    "owned_by": null,
    "percent_owned": 2,
    "stats": {
      "stat_60": "98/365",
      "stat_7": 31,
      "stat_8": 98,
      "stat_12": 5,
      "stat_13": 36,
      "stat_16": 0,
      "stat_18": 32,
      "stat_21": 71,
      "stat_23": 130,
      "stat_3": 0.268,
      "stat_55": 0.689
    }
  },
  {
    "player_key": "458.p.12470",
    "player_id": "12470",
    "name": "Joe Mack",
    "first_name": "Joe",
    "last_name": "Mack",
    "position": "C",
    "eligible_positions": [],
    "team": "MIA",
    "team_full": "Miami Marlins",
    "status": "",
    "ownership_type": "freeagents",
    "owned_by": null,
    "percent_owned": 0,
    "stats": {
      "stat_60": "-/-",
      "stat_7": "-",
      "stat_8": "-",
      "stat_12": "-",
      "stat_13": "-",
      "stat_16": "-",
      "stat_18": "-",
      "stat_21": "-",
      "stat_23": "-",
      "stat_3": "-",
      "stat_55": "-"
    }
  },
  {
    "player_key": "458.p.12477",
    "player_id": "12477",
    "name": "Jeferson Quero",
    "first_name": "Jeferson",
    "last_name": "Quero",
    "position": "C",
    "eligible_positions": [],
    "team": "MIL",
    "team_full": "Milwaukee Brewers",
    "status": "",
    "ownership_type": "freeagents",
    "owned_by": null,
    "percent_owned": 0,
    "stats": {
      "stat_60": "-/-",
      "stat_7": "-",
      "stat_8": "-",
      "stat_12": "-",
      "stat_13": "-",
      "stat_16": "-",
      "stat_18": "-",
      "stat_21": "-",
      "stat_23": "-",
      "stat_3": "-",
      "stat_55": "-"
    }
  },
  {
    "player_key": "458.p.12514",
    "player_id": "12514",
    "name": "Henry Davis",
    "first_name": "Henry",
    "last_name": "Davis",
    "position": "C",
    "eligible_positions": [],
    "team": "PIT",
    "team_full": "Pittsburgh Pirates",
    "status": "",
    "ownership_type": "freeagents",
    "owned_by": null,
    "percent_owned": 0,
    "stats": {
      "stat_60": "42/252",
      "stat_7": 25,
      "stat_8": 42,
      "stat_12": 7,
      "stat_13": 22,
      "stat_16": 2,
      "stat_18": 18,
      "stat_21": 76,
      "stat_23": 70,
      "stat_3": 0.167,
      "stat_55": 0.512
    }
  },
  {
    "player_key": "458.p.12532",
    "player_id": "12532",
    "name": "Harry Ford",
    "first_name": "Harry",
    "last_name": "Ford",
    "position": "C",
    "eligible_positions": [],
    "team": "WSH",
    "team_full": "Washington Nationals",
    "status": "",
    "ownership_type": "freeagents",
    "owned_by": null,
    "percent_owned": 1,
    "stats": {
      "stat_60": "1/6",
      "stat_7": 1,
      "stat_8": 1,
      "stat_12": 0,
      "stat_13": 1,
      "stat_16": 0,
      "stat_18": 0,
      "stat_21": 3,
      "stat_23": 1,
      "stat_3": 0.167,
      "stat_55": 0.417
    }
  },
  {
    "player_key": "458.p.12587",
    "player_id": "12587",
    "name": "Drew Millas",
    "first_name": "Drew",
    "last_name": "Millas",
    "position": "C",
    "eligible_positions": [],
    "team": "WSH",
    "team_full": "Washington Nationals",
    "status": "IL60",
    "ownership_type": "freeagents",
    "owned_by": null,
    "percent_owned": 0,
    "stats": {
      "stat_60": "15/49",
      "stat_7": 6,
      "stat_8": 15,
      "stat_12": 0,
      "stat_13": 7,
      "stat_16": 2,
      "stat_18": 4,
      "stat_21": 7,
      "stat_23": 22,
      "stat_3": 0.306,
      "stat_55": 0.807
    }
  },
  {
    "player_key": "458.p.12637",
    "player_id": "12637",
    "name": "Jason Delay",
    "first_name": "Jason",
    "last_name": "Delay",
    "position": "C",
    "eligible_positions": [],
    "team": "BOS",
    "team_full": "Boston Red Sox",
    "status": "NA",
    "ownership_type": "freeagents",
    "owned_by": null,
    "percent_owned": 0,
    "stats": {
      "stat_60": "-/-",
      "stat_7": "-",
      "stat_8": "-",
      "stat_12": "-",
      "stat_13": "-",
      "stat_16": "-",
      "stat_18": "-",
      "stat_21": "-",
      "stat_23": "-",
      "stat_3": "-",
      "stat_55": "-"
    }
  },
  {
    "player_key": "458.p.12669",
    "player_id": "12669",
    "name": "Chuckie Robinson",
    "first_name": "Chuckie",
    "last_name": "Robinson",
    "position": "C",
    "eligible_positions": [],
    "team": "LAD",
    "team_full": "Los Angeles Dodgers",
    "status": "NA",
    "ownership_type": "freeagents",
    "owned_by": null,
    "percent_owned": 0,
    "stats": {
      "stat_60": "0/1",
      "stat_7": 1,
      "stat_8": 0,
      "stat_12": 0,
      "stat_13": 0,
      "stat_16": 0,
      "stat_18": 0,
      "stat_21": 0,
      "stat_23": 0,
      "stat_3": 0.0,
      "stat_55": 0.0
    }
  },
  {
    "player_key": "458.p.12767",
    "player_id": "12767",
    "name": "Blake Sabol",
    "first_name": "Blake",
    "last_name": "Sabol",
    "position": "C",
    "eligible_positions": [],
    "team": "BOS",
    "team_full": "Boston Red Sox",
    "status": "NA",
    "ownership_type": "freeagents",
    "owned_by": null,
    "percent_owned": 0,
    "stats": {
      "stat_60": "2/16",
      "stat_7": 2,
      "stat_8": 2,
      "stat_12": 0,
      "stat_13": 1,
      "stat_16": 0,
      "stat_18": 1,
      "stat_21": 7,
      "stat_23": 3,
      "stat_3": 0.125,
      "stat_55": 0.355
    }
  },
  {
    "player_key": "458.p.60077",
    "player_id": "60077",
    "name": "Drake Baldwin",
    "first_name": "Drake",
    "last_name": "Baldwin",
    "position": "C",
    "eligible_positions": [],
    "team": "ATL",
    "team_full": "Atlanta Braves",
    "status": "",
    "ownership_type": "team",
    "owned_by": "458.l.15505.t.4",
    "percent_owned": 48,
    "stats": {
      "stat_60": "111/405",
      "stat_7": 56,
      "stat_8": 111,
      "stat_12": 19,
      "stat_13": 80,
      "stat_16": 0,
      "stat_18": 38,
      "stat_21": 68,
      "stat_23": 190,
      "stat_3": 0.274,
      "stat_55": 0.81
    }
  },
  {
    "player_key": "458.p.60120",
    "player_id": "60120",
    "name": "Mois\u00e9s Ballesteros",
    "first_name": "Mois\u00e9s",
    "last_name": "Ballesteros",
    "position": "C",
    "eligible_positions": [],
    "team": "CHC",
    "team_full": "Chicago Cubs",
    "status": "",
    "ownership_type": "freeagents",
    "owned_by": null,
    "percent_owned": 6,
    "stats": {
      "stat_60": "17/57",
      "stat_7": 12,
      "stat_8": 17,
      "stat_12": 2,
      "stat_13": 11,
      "stat_16": 0,
      "stat_18": 9,
      "stat_21": 12,
      "stat_23": 27,
      "stat_3": 0.298,
      "stat_55": 0.868
    }
  },
  {
    "player_key": "458.p.60278",
    "player_id": "60278",
    "name": "Kevin Parada",
    "first_name": "Kevin",
    "last_name": "Parada",
    "position": "C",
    "eligible_positions": [],
    "team": "NYM",
    "team_full": "New York Mets",
    "status": "NA",
    "ownership_type": "freeagents",
    "owned_by": null,
    "percent_owned": 0,
    "stats": {
      "stat_60": "-/-",
      "stat_7": "-",
      "stat_8": "-",
      "stat_12": "-",
      "stat_13": "-",
      "stat_16": "-",
      "stat_18": "-",
      "stat_21": "-",
      "stat_23": "-",
      "stat_3": "-",
      "stat_55": "-"
    }
  },
  {
    "player_key": "458.p.60308",
    "player_id": "60308",
    "name": "Daniel Susac",
    "first_name": "Daniel",
    "last_name": "Susac",
    "position": "C",
    "eligible_positions": [],
    "team": "SF",
    "team_full": "San Francisco Giants",
    "status": "",
    "ownership_type": "freeagents",
    "owned_by": null,
    "percent_owned": 0,
    "stats": {
      "stat_60": "-/-",
      "stat_7": "-",
      "stat_8": "-",
      "stat_12": "-",
      "stat_13": "-",
      "stat_16": "-",
      "stat_18": "-",
      "stat_21": "-",
      "stat_23": "-",
      "stat_3": "-",
      "stat_55": "-"
    }
  },
  {
    "player_key": "458.p.60334",
    "player_id": "60334",
    "name": "Caleb Ricketts",
    "first_name": "Caleb",
    "last_name": "Ricketts",
    "position": "C",
    "eligible_positions": [],
    "team": "PHI",
    "team_full": "Philadelphia Phillies",
    "status": "NA",
    "ownership_type": "freeagents",
    "owned_by": null,
    "percent_owned": 0,
    "stats": {
      "stat_60": "-/-",
      "stat_7": "-",
      "stat_8": "-",
      "stat_12": "-",
      "stat_13": "-",
      "stat_16": "-",
      "stat_18": "-",
      "stat_21": "-",
      "stat_23": "-",
      "stat_3": "-",
      "stat_55": "-"
    }
  },
  {
    "player_key": "458.p.60403",
    "player_id": "60403",
    "name": "Leonardo Bernal",
    "first_name": "Leonardo",
    "last_name": "Bernal",
    "position": "C",
    "eligible_positions": [],
    "team": "STL",
    "team_full": "St. Louis Cardinals",
    "status": "",
    "ownership_type": "freeagents",
    "owned_by": null,
    "percent_owned": 0,
    "stats": {
      "stat_60": "-/-",
      "stat_7": "-",
      "stat_8": "-",
      "stat_12": "-",
      "stat_13": "-",
      "stat_16": "-",
      "stat_18": "-",
      "stat_21": "-",
      "stat_23": "-",
      "stat_3": "-",
      "stat_55": "-"
    }
  },
  {
    "player_key": "458.p.60406",
    "player_id": "60406",
    "name": "Jimmy Crooks",
    "first_name": "Jimmy",
    "last_name": "Crooks",
    "position": "C",
    "eligible_positions": [],
    "team": "STL",
    "team_full": "St. Louis Cardinals",
    "status": "",
    "ownership_type": "freeagents",
    "owned_by": null,
    "percent_owned": 0,
    "stats": {
      "stat_60": "6/45",
      "stat_7": 3,
      "stat_8": 6,
      "stat_12": 1,
      "stat_13": 1,
      "stat_16": 0,
      "stat_18": 0,
      "stat_21": 17,
      "stat_23": 11,
      "stat_3": 0.133,
      "stat_55": 0.396
    }
  },
  {
    "player_key": "458.p.60422",
    "player_id": "60422",
    "name": "Dominic Keegan",
    "first_name": "Dominic",
    "last_name": "Keegan",
    "position": "C",
    "eligible_positions": [],
    "team": "TB",
    "team_full": "Tampa Bay Rays",
    "status": "",
    "ownership_type": "freeagents",
    "owned_by": null,
    "percent_owned": 0,
    "stats": {
      "stat_60": "-/-",
      "stat_7": "-",
      "stat_8": "-",
      "stat_12": "-",
      "stat_13": "-",
      "stat_16": "-",
      "stat_18": "-",
      "stat_21": "-",
      "stat_23": "-",
      "stat_3": "-",
      "stat_55": "-"
    }
  },
  {
    "player_key": "458.p.60536",
    "player_id": "60536",
    "name": "Carlos Narv\u00e1ez",
    "first_name": "Carlos",
    "last_name": "Narv\u00e1ez",
    "position": "C",
    "eligible_positions": [],
    "team": "BOS",
    "team_full": "Boston Red Sox",
    "status": "DTD",
    "ownership_type": "freeagents",
    "owned_by": null,
    "percent_owned": 8,
    "stats": {
      "stat_60": "97/403",
      "stat_7": 51,
      "stat_8": 97,
      "stat_12": 15,
      "stat_13": 50,
      "stat_16": 1,
      "stat_18": 38,
      "stat_21": 111,
      "stat_23": 169,
      "stat_3": 0.241,
      "stat_55": 0.725
    }
  },
  {
    "player_key": "458.p.60687",
    "player_id": "60687",
    "name": "Braxton Fulford",
    "first_name": "Braxton",
    "last_name": "Fulford",
    "position": "C",
    "eligible_positions": [],
    "team": "COL",
    "team_full": "Colorado Rockies",
    "status": "",
    "ownership_type": "freeagents",
    "owned_by": null,
    "percent_owned": 0,
    "stats": {
      "stat_60": "23/108",
      "stat_7": 11,
      "stat_8": 23,
      "stat_12": 1,
      "stat_13": 16,
      "stat_16": 1,
      "stat_18": 7,
      "stat_21": 36,
      "stat_23": 35,
      "stat_3": 0.213,
      "stat_55": 0.591
    }
  },
  {
    "player_key": "458.p.60885",
    "player_id": "60885",
    "name": "Logan Driscoll",
    "first_name": "Logan",
    "last_name": "Driscoll",
    "position": "C",
    "eligible_positions": [],
    "team": "TB",
    "team_full": "Tampa Bay Rays",
    "status": "NA",
    "ownership_type": "freeagents",
    "owned_by": null,
    "percent_owned": 0,
    "stats": {
      "stat_60": "-/-",
      "stat_7": "-",
      "stat_8": "-",
      "stat_12": "-",
      "stat_13": "-",
      "stat_16": "-",
      "stat_18": "-",
      "stat_21": "-",
      "stat_23": "-",
      "stat_3": "-",
      "stat_55": "-"
    }
  },
  {
    "player_key": "458.p.60901",
    "player_id": "60901",
    "name": "Maverick Handley",
    "first_name": "Maverick",
    "last_name": "Handley",
    "position": "C",
    "eligible_positions": [],
    "team": "BAL",
    "team_full": "Baltimore Orioles",
    "status": "NA",
    "ownership_type": "freeagents",
    "owned_by": null,
    "percent_owned": 0,
    "stats": {
      "stat_60": "3/41",
      "stat_7": 2,
      "stat_8": 3,
      "stat_12": 0,
      "stat_13": 3,
      "stat_16": 0,
      "stat_18": 2,
      "stat_21": 18,
      "stat_23": 3,
      "stat_3": 0.073,
      "stat_55": 0.206
    }
  },
  {
    "player_key": "458.p.61258",
    "player_id": "61258",
    "name": "Hayden Senger",
    "first_name": "Hayden",
    "last_name": "Senger",
    "position": "C",
    "eligible_positions": [],
    "team": "NYM",
    "team_full": "New York Mets",
    "status": "",
    "ownership_type": "freeagents",
    "owned_by": null,
    "percent_owned": 0,
    "stats": {
      "stat_60": "13/72",
      "stat_7": 8,
      "stat_8": 13,
      "stat_12": 0,
      "stat_13": 4,
      "stat_16": 0,
      "stat_18": 3,
      "stat_21": 22,
      "stat_23": 14,
      "stat_3": 0.181,
      "stat_55": 0.415
    }
  },
  {
    "player_key": "458.p.61268",
    "player_id": "61268",
    "name": "Hunter Feduccia",
    "first_name": "Hunter",
    "last_name": "Feduccia",
    "position": "C",
    "eligible_positions": [],
    "team": "TB",
    "team_full": "Tampa Bay Rays",
    "status": "",
    "ownership_type": "freeagents",
    "owned_by": null,
    "percent_owned": 0,
    "stats": {
      "stat_60": "13/88",
      "stat_7": 5,
      "stat_8": 13,
      "stat_12": 0,
      "stat_13": 8,
      "stat_16": 1,
      "stat_18": 15,
      "stat_21": 29,
      "stat_23": 18,
      "stat_3": 0.148,
      "stat_55": 0.472
    }
  },
  {
    "player_key": "458.p.61602",
    "player_id": "61602",
    "name": "Nick Raposo",
    "first_name": "Nick",
    "last_name": "Raposo",
    "position": "C",
    "eligible_positions": [],
    "team": "SEA",
    "team_full": "Seattle Mariners",
    "status": "NA",
    "ownership_type": "freeagents",
    "owned_by": null,
    "percent_owned": 0,
    "stats": {
      "stat_60": "-/-",
      "stat_7": "-",
      "stat_8": "-",
      "stat_12": "-",
      "stat_13": "-",
      "stat_16": "-",
      "stat_18": "-",
      "stat_21": "-",
      "stat_23": "-",
      "stat_3": "-",
      "stat_55": "-"
    }
  },
  {
    "player_key": "458.p.61613",
    "player_id": "61613",
    "name": "Pedro Pag\u00e9s",
    "first_name": "Pedro",
    "last_name": "Pag\u00e9s",
    "position": "C",
    "eligible_positions": [],
    "team": "STL",
    "team_full": "St. Louis Cardinals",
    "status": "",
    "ownership_type": "freeagents",
    "owned_by": null,
    "percent_owned": 2,
    "stats": {
      "stat_60": "83/361",
      "stat_7": 38,
      "stat_8": 83,
      "stat_12": 11,
      "stat_13": 45,
      "stat_16": 0,
      "stat_18": 19,
      "stat_21": 107,
      "stat_23": 131,
      "stat_3": 0.23,
      "stat_55": 0.635
    }
  },
  {
    "player_key": "458.p.61636",
    "player_id": "61636",
    "name": "Logan Porter",
    "first_name": "Logan",
    "last_name": "Porter",
    "position": "C",
    "eligible_positions": [],
    "team": "SF",
    "team_full": "San Francisco Giants",
    "status": "NA",
    "ownership_type": "freeagents",
    "owned_by": null,
    "percent_owned": 0,
    "stats": {
      "stat_60": "1/7",
      "stat_7": 2,
      "stat_8": 1,
      "stat_12": 0,
      "stat_13": 1,
      "stat_16": 0,
      "stat_18": 1,
      "stat_21": 2,
      "stat_23": 1,
      "stat_3": 0.143,
      "stat_55": 0.476
    }
  },
  {
    "player_key": "458.p.61673",
    "player_id": "61673",
    "name": "David Ba\u00f1uelos",
    "first_name": "David",
    "last_name": "Ba\u00f1uelos",
    "position": "C",
    "eligible_positions": [],
    "team": "BAL",
    "team_full": "Baltimore Orioles",
    "status": "NA",
    "ownership_type": "freeagents",
    "owned_by": null,
    "percent_owned": 0,
    "stats": {
      "stat_60": "0/1",
      "stat_7": 0,
      "stat_8": 0,
      "stat_12": 0,
      "stat_13": 0,
      "stat_16": 0,
      "stat_18": 0,
      "stat_21": 1,
      "stat_23": 0,
      "stat_3": 0.0,
      "stat_55": 0.5
    }
  },
  {
    "player_key": "458.p.61775",
    "player_id": "61775",
    "name": "Rafael Flores Jr.",
    "first_name": "Rafael",
    "last_name": "Flores Jr.",
    "position": "C",
    "eligible_positions": [],
    "team": "PIT",
    "team_full": "Pittsburgh Pirates",
    "status": "",
    "ownership_type": "freeagents",
    "owned_by": null,
    "percent_owned": 0,
    "stats": {
      "stat_60": "3/15",
      "stat_7": 0,
      "stat_8": 3,
      "stat_12": 0,
      "stat_13": 0,
      "stat_16": 0,
      "stat_18": 2,
      "stat_21": 7,
      "stat_23": 5,
      "stat_3": 0.2,
      "stat_55": 0.627
    }
  },
  {
    "player_key": "458.p.61785",
    "player_id": "61785",
    "name": "Mickey Gasper",
    "first_name": "Mickey",
    "last_name": "Gasper",
    "position": "C",
    "eligible_positions": [],
    "team": "MIN",
    "team_full": "Minnesota Twins",
    "status": "",
    "ownership_type": "freeagents",
    "owned_by": null,
    "percent_owned": 0,
    "stats": {
      "stat_60": "15/95",
      "stat_7": 15,
      "stat_8": 15,
      "stat_12": 2,
      "stat_13": 11,
      "stat_16": 2,
      "stat_18": 10,
      "stat_21": 20,
      "stat_23": 22,
      "stat_3": 0.158,
      "stat_55": 0.489
    }
  },
  {
    "player_key": "458.p.61796",
    "player_id": "61796",
    "name": "C\u00e9sar Salazar",
    "first_name": "C\u00e9sar",
    "last_name": "Salazar",
    "position": "C",
    "eligible_positions": [],
    "team": "HOU",
    "team_full": "Houston Astros",
    "status": "",
    "ownership_type": "freeagents",
    "owned_by": null,
    "percent_owned": 0,
    "stats": {
      "stat_60": "3/13",
      "stat_7": 0,
      "stat_8": 3,
      "stat_12": 0,
      "stat_13": 1,
      "stat_16": 0,
      "stat_18": 2,
      "stat_21": 2,
      "stat_23": 3,
      "stat_3": 0.231,
      "stat_55": 0.606
    }
  },
  {
    "player_key": "458.p.61797",
    "player_id": "61797",
    "name": "CJ Stubbs",
    "first_name": "CJ",
    "last_name": "Stubbs",
    "position": "C",
    "eligible_positions": [],
    "team": "WSH",
    "team_full": "Washington Nationals",
    "status": "NA",
    "ownership_type": "freeagents",
    "owned_by": null,
    "percent_owned": 0,
    "stats": {
      "stat_60": "0/3",
      "stat_7": 0,
      "stat_8": 0,
      "stat_12": 0,
      "stat_13": 0,
      "stat_16": 0,
      "stat_18": 0,
      "stat_21": 0,
      "stat_23": 0,
      "stat_3": 0.0,
      "stat_55": 0.0
    }
  },
  {
    "player_key": "458.p.61813",
    "player_id": "61813",
    "name": "Jesus Rodriguez",
    "first_name": "Jesus",
    "last_name": "Rodriguez",
    "position": "C",
    "eligible_positions": [],
    "team": "SF",
    "team_full": "San Francisco Giants",
    "status": "",
    "ownership_type": "freeagents",
    "owned_by": null,
    "percent_owned": 0,
    "stats": {
      "stat_60": "-/-",
      "stat_7": "-",
      "stat_8": "-",
      "stat_12": "-",
      "stat_13": "-",
      "stat_16": "-",
      "stat_18": "-",
      "stat_21": "-",
      "stat_23": "-",
      "stat_3": "-",
      "stat_55": "-"
    }
  },
  {
    "player_key": "458.p.61917",
    "player_id": "61917",
    "name": "Pablo Aliendo",
    "first_name": "Pablo",
    "last_name": "Aliendo",
    "position": "C",
    "eligible_positions": [],
    "team": "CHC",
    "team_full": "Chicago Cubs",
    "status": "NA",
    "ownership_type": "freeagents",
    "owned_by": null,
    "percent_owned": 0,
    "stats": {
      "stat_60": "-/-",
      "stat_7": "-",
      "stat_8": "-",
      "stat_12": "-",
      "stat_13": "-",
      "stat_16": "-",
      "stat_18": "-",
      "stat_21": "-",
      "stat_23": "-",
      "stat_3": "-",
      "stat_55": "-"
    }
  },
  {
    "player_key": "458.p.62109",
    "player_id": "62109",
    "name": "Jesus Lopez",
    "first_name": "Jesus",
    "last_name": "Lopez",
    "position": "C",
    "eligible_positions": [],
    "team": "TEX",
    "team_full": "Texas Rangers",
    "status": "NA",
    "ownership_type": "freeagents",
    "owned_by": null,
    "percent_owned": 0,
    "stats": {
      "stat_60": "-/-",
      "stat_7": "-",
      "stat_8": "-",
      "stat_12": "-",
      "stat_13": "-",
      "stat_16": "-",
      "stat_18": "-",
      "stat_21": "-",
      "stat_23": "-",
      "stat_3": "-",
      "stat_55": "-"
    }
  },
  {
    "player_key": "458.p.62189",
    "player_id": "62189",
    "name": "Jair Camargo",
    "first_name": "Jair",
    "last_name": "Camargo",
    "position": "C",
    "eligible_positions": [],
    "team": "MIN",
    "team_full": "Minnesota Twins",
    "status": "IL60",
    "ownership_type": "freeagents",
    "owned_by": null,
    "percent_owned": 0,
    "stats": {
      "stat_60": "-/-",
      "stat_7": "-",
      "stat_8": "-",
      "stat_12": "-",
      "stat_13": "-",
      "stat_16": "-",
      "stat_18": "-",
      "stat_21": "-",
      "stat_23": "-",
      "stat_3": "-",
      "stat_55": "-"
    }
  },
  {
    "player_key": "458.p.62225",
    "player_id": "62225",
    "name": "Ethan Salas",
    "first_name": "Ethan",
    "last_name": "Salas",
    "position": "C",
    "eligible_positions": [],
    "team": "SD",
    "team_full": "San Diego Padres",
    "status": "NA",
    "ownership_type": "freeagents",
    "owned_by": null,
    "percent_owned": 1,
    "stats": {
      "stat_60": "-/-",
      "stat_7": "-",
      "stat_8": "-",
      "stat_12": "-",
      "stat_13": "-",
      "stat_16": "-",
      "stat_18": "-",
      "stat_21": "-",
      "stat_23": "-",
      "stat_3": "-",
      "stat_55": "-"
    }
  },
  {
    "player_key": "458.p.62882",
    "player_id": "62882",
    "name": "Cooper Ingle",
    "first_name": "Cooper",
    "last_name": "Ingle",
    "position": "C",
    "eligible_positions": [],
    "team": "CLE",
    "team_full": "Cleveland Guardians",
    "status": "NA",
    "ownership_type": "freeagents",
    "owned_by": null,
    "percent_owned": 0,
    "stats": {
      "stat_60": "-/-",
      "stat_7": "-",
      "stat_8": "-",
      "stat_12": "-",
      "stat_13": "-",
      "stat_16": "-",
      "stat_18": "-",
      "stat_21": "-",
      "stat_23": "-",
      "stat_3": "-",
      "stat_55": "-"
    }
  },
  {
    "player_key": "458.p.62960",
    "player_id": "62960",
    "name": "Blake Mitchell",
    "first_name": "Blake",
    "last_name": "Mitchell",
    "position": "C",
    "eligible_positions": [],
    "team": "KC",
    "team_full": "Kansas City Royals",
    "status": "NA",
    "ownership_type": "freeagents",
    "owned_by": null,
    "percent_owned": 0,
    "stats": {
      "stat_60": "-/-",
      "stat_7": "-",
      "stat_8": "-",
      "stat_12": "-",
      "stat_13": "-",
      "stat_16": "-",
      "stat_18": "-",
      "stat_21": "-",
      "stat_23": "-",
      "stat_3": "-",
      "stat_55": "-"
    }
  },
  {
    "player_key": "458.p.62979",
    "player_id": "62979",
    "name": "Kyle Teel",
    "first_name": "Kyle",
    "last_name": "Teel",
    "position": "C",
    "eligible_positions": [],
    "team": "CWS",
    "team_full": "Chicago White Sox",
    "status": "",
    "ownership_type": "team",
    "owned_by": "458.l.15505.t.10",
    "percent_owned": 24,
    "stats": {
      "stat_60": "69/253",
      "stat_7": 38,
      "stat_8": 69,
      "stat_12": 8,
      "stat_13": 35,
      "stat_16": 3,
      "stat_18": 37,
      "stat_21": 77,
      "stat_23": 104,
      "stat_3": 0.273,
      "stat_55": 0.786
    }
  },
  {
    "player_key": "458.p.63117",
    "player_id": "63117",
    "name": "J.D. Gonzalez",
    "first_name": "J.D.",
    "last_name": "Gonzalez",
    "position": "C",
    "eligible_positions": [],
    "team": "TB",
    "team_full": "Tampa Bay Rays",
    "status": "NA",
    "ownership_type": "freeagents",
    "owned_by": null,
    "percent_owned": 0,
    "stats": {
      "stat_60": "-/-",
      "stat_7": "-",
      "stat_8": "-",
      "stat_12": "-",
      "stat_13": "-",
      "stat_16": "-",
      "stat_18": "-",
      "stat_21": "-",
      "stat_23": "-",
      "stat_3": "-",
      "stat_55": "-"
    }
  },
  {
    "player_key": "458.p.63267",
    "player_id": "63267",
    "name": "Sammy Hernandez",
    "first_name": "Sammy",
    "last_name": "Hernandez",
    "position": "C",
    "eligible_positions": [],
    "team": "STL",
    "team_full": "St. Louis Cardinals",
    "status": "NA",
    "ownership_type": "freeagents",
    "owned_by": null,
    "percent_owned": 0,
    "stats": {
      "stat_60": "-/-",
      "stat_7": "-",
      "stat_8": "-",
      "stat_12": "-",
      "stat_13": "-",
      "stat_16": "-",
      "stat_18": "-",
      "stat_21": "-",
      "stat_23": "-",
      "stat_3": "-",
      "stat_55": "-"
    }
  },
  {
    "player_key": "458.p.63524",
    "player_id": "63524",
    "name": "Christian Cerda",
    "first_name": "Christian",
    "last_name": "Cerda",
    "position": "C",
    "eligible_positions": [],
    "team": "AZ",
    "team_full": "Arizona Diamondbacks",
    "status": "NA",
    "ownership_type": "freeagents",
    "owned_by": null,
    "percent_owned": 0,
    "stats": {
      "stat_60": "-/-",
      "stat_7": "-",
      "stat_8": "-",
      "stat_12": "-",
      "stat_13": "-",
      "stat_16": "-",
      "stat_18": "-",
      "stat_21": "-",
      "stat_23": "-",
      "stat_3": "-",
      "stat_55": "-"
    }
  },
  {
    "player_key": "458.p.63535",
    "player_id": "63535",
    "name": "Johanfran Garcia",
    "first_name": "Johanfran",
    "last_name": "Garcia",
    "position": "C",
    "eligible_positions": [],
    "team": "BOS",
    "team_full": "Boston Red Sox",
    "status": "NA",
    "ownership_type": "freeagents",
    "owned_by": null,
    "percent_owned": 0,
    "stats": {
      "stat_60": "-/-",
      "stat_7": "-",
      "stat_8": "-",
      "stat_12": "-",
      "stat_13": "-",
      "stat_16": "-",
      "stat_18": "-",
      "stat_21": "-",
      "stat_23": "-",
      "stat_3": "-",
      "stat_55": "-"
    }
  },
  {
    "player_key": "458.p.63545",
    "player_id": "63545",
    "name": "Alfredo Duno",
    "first_name": "Alfredo",
    "last_name": "Duno",
    "position": "C",
    "eligible_positions": [],
    "team": "CIN",
    "team_full": "Cincinnati Reds",
    "status": "NA",
    "ownership_type": "freeagents",
    "owned_by": null,
    "percent_owned": 0,
    "stats": {
      "stat_60": "-/-",
      "stat_7": "-",
      "stat_8": "-",
      "stat_12": "-",
      "stat_13": "-",
      "stat_16": "-",
      "stat_18": "-",
      "stat_21": "-",
      "stat_23": "-",
      "stat_3": "-",
      "stat_55": "-"
    }
  },
  {
    "player_key": "458.p.63569",
    "player_id": "63569",
    "name": "Dario Laverde",
    "first_name": "Dario",
    "last_name": "Laverde",
    "position": "C",
    "eligible_positions": [],
    "team": "LAA",
    "team_full": "Los Angeles Angels",
    "status": "NA",
    "ownership_type": "freeagents",
    "owned_by": null,
    "percent_owned": 0,
    "stats": {
      "stat_60": "-/-",
      "stat_7": "-",
      "stat_8": "-",
      "stat_12": "-",
      "stat_13": "-",
      "stat_16": "-",
      "stat_18": "-",
      "stat_21": "-",
      "stat_23": "-",
      "stat_3": "-",
      "stat_55": "-"
    }
  },
  {
    "player_key": "458.p.63571",
    "player_id": "63571",
    "name": "Juan Flores",
    "first_name": "Juan",
    "last_name": "Flores",
    "position": "C",
    "eligible_positions": [],
    "team": "LAA",
    "team_full": "Los Angeles Angels",
    "status": "NA",
    "ownership_type": "freeagents",
    "owned_by": null,
    "percent_owned": 0,
    "stats": {
      "stat_60": "-/-",
      "stat_7": "-",
      "stat_8": "-",
      "stat_12": "-",
      "stat_13": "-",
      "stat_16": "-",
      "stat_18": "-",
      "stat_21": "-",
      "stat_23": "-",
      "stat_3": "-",
      "stat_55": "-"
    }
  },
  {
    "player_key": "458.p.63580",
    "player_id": "63580",
    "name": "Thayron Liranzo",
    "first_name": "Thayron",
    "last_name": "Liranzo",
    "position": "C",
    "eligible_positions": [],
    "team": "DET",
    "team_full": "Detroit Tigers",
    "status": "",
    "ownership_type": "freeagents",
    "owned_by": null,
    "percent_owned": 0,
    "stats": {
      "stat_60": "-/-",
      "stat_7": "-",
      "stat_8": "-",
      "stat_12": "-",
      "stat_13": "-",
      "stat_16": "-",
      "stat_18": "-",
      "stat_21": "-",
      "stat_23": "-",
      "stat_3": "-",
      "stat_55": "-"
    }
  },
  {
    "player_key": "458.p.63618",
    "player_id": "63618",
    "name": "Eduardo Tait",
    "first_name": "Eduardo",
    "last_name": "Tait",
    "position": "C",
    "eligible_positions": [],
    "team": "MIN",
    "team_full": "Minnesota Twins",
    "status": "NA",
    "ownership_type": "freeagents",
    "owned_by": null,
    "percent_owned": 0,
    "stats": {
      "stat_60": "-/-",
      "stat_7": "-",
      "stat_8": "-",
      "stat_12": "-",
      "stat_13": "-",
      "stat_16": "-",
      "stat_18": "-",
      "stat_21": "-",
      "stat_23": "-",
      "stat_3": "-",
      "stat_55": "-"
    }
  },
  {
    "player_key": "458.p.63628",
    "player_id": "63628",
    "name": "Onil Perez",
    "first_name": "Onil",
    "last_name": "Perez",
    "position": "C",
    "eligible_positions": [],
    "team": "SF",
    "team_full": "San Francisco Giants",
    "status": "NA",
    "ownership_type": "freeagents",
    "owned_by": null,
    "percent_owned": 0,
    "stats": {
      "stat_60": "-/-",
      "stat_7": "-",
      "stat_8": "-",
      "stat_12": "-",
      "stat_13": "-",
      "stat_16": "-",
      "stat_18": "-",
      "stat_21": "-",
      "stat_23": "-",
      "stat_3": "-",
      "stat_55": "-"
    }
  },
  {
    "player_key": "458.p.64323",
    "player_id": "64323",
    "name": "Caleb Lomavita",
    "first_name": "Caleb",
    "last_name": "Lomavita",
    "position": "C",
    "eligible_positions": [],
    "team": "WSH",
    "team_full": "Washington Nationals",
    "status": "NA",
    "ownership_type": "freeagents",
    "owned_by": null,
    "percent_owned": 0,
    "stats": {
      "stat_60": "-/-",
      "stat_7": "-",
      "stat_8": "-",
      "stat_12": "-",
      "stat_13": "-",
      "stat_16": "-",
      "stat_18": "-",
      "stat_21": "-",
      "stat_23": "-",
      "stat_3": "-",
      "stat_55": "-"
    }
  },
  {
    "player_key": "458.p.64334",
    "player_id": "64334",
    "name": "Walker Janek",
    "first_name": "Walker",
    "last_name": "Janek",
    "position": "C",
    "eligible_positions": [],
    "team": "HOU",
    "team_full": "Houston Astros",
    "status": "NA",
    "ownership_type": "freeagents",
    "owned_by": null,
    "percent_owned": 0,
    "stats": {
      "stat_60": "-/-",
      "stat_7": "-",
      "stat_8": "-",
      "stat_12": "-",
      "stat_13": "-",
      "stat_16": "-",
      "stat_18": "-",
      "stat_21": "-",
      "stat_23": "-",
      "stat_3": "-",
      "stat_55": "-"
    }
  },
  {
    "player_key": "458.p.64341",
    "player_id": "64341",
    "name": "Malcolm Moore",
    "first_name": "Malcolm",
    "last_name": "Moore",
    "position": "C",
    "eligible_positions": [],
    "team": "TEX",
    "team_full": "Texas Rangers",
    "status": "NA",
    "ownership_type": "freeagents",
    "owned_by": null,
    "percent_owned": 0,
    "stats": {
      "stat_60": "-/-",
      "stat_7": "-",
      "stat_8": "-",
      "stat_12": "-",
      "stat_13": "-",
      "stat_16": "-",
      "stat_18": "-",
      "stat_21": "-",
      "stat_23": "-",
      "stat_3": "-",
      "stat_55": "-"
    }
  },
  {
    "player_key": "458.p.64348",
    "player_id": "64348",
    "name": "Jacob Cozart",
    "first_name": "Jacob",
    "last_name": "Cozart",
    "position": "C",
    "eligible_positions": [],
    "team": "CLE",
    "team_full": "Cleveland Guardians",
    "status": "NA",
    "ownership_type": "freeagents",
    "owned_by": null,
    "percent_owned": 0,
    "stats": {
      "stat_60": "-/-",
      "stat_7": "-",
      "stat_8": "-",
      "stat_12": "-",
      "stat_13": "-",
      "stat_16": "-",
      "stat_18": "-",
      "stat_21": "-",
      "stat_23": "-",
      "stat_3": "-",
      "stat_55": "-"
    }
  },
  {
    "player_key": "458.p.64357",
    "player_id": "64357",
    "name": "Kevin Bazzell",
    "first_name": "Kevin",
    "last_name": "Bazzell",
    "position": "C",
    "eligible_positions": [],
    "team": "WSH",
    "team_full": "Washington Nationals",
    "status": "NA",
    "ownership_type": "freeagents",
    "owned_by": null,
    "percent_owned": 0,
    "stats": {
      "stat_60": "-/-",
      "stat_7": "-",
      "stat_8": "-",
      "stat_12": "-",
      "stat_13": "-",
      "stat_16": "-",
      "stat_18": "-",
      "stat_21": "-",
      "stat_23": "-",
      "stat_3": "-",
      "stat_55": "-"
    }
  },
  {
    "player_key": "458.p.64447",
    "player_id": "64447",
    "name": "Cole Messina",
    "first_name": "Cole",
    "last_name": "Messina",
    "position": "C",
    "eligible_positions": [],
    "team": "COL",
    "team_full": "Colorado Rockies",
    "status": "NA",
    "ownership_type": "freeagents",
    "owned_by": null,
    "percent_owned": 0,
    "stats": {
      "stat_60": "-/-",
      "stat_7": "-",
      "stat_8": "-",
      "stat_12": "-",
      "stat_13": "-",
      "stat_16": "-",
      "stat_18": "-",
      "stat_21": "-",
      "stat_23": "-",
      "stat_3": "-",
      "stat_55": "-"
    }
  },
  {
    "player_key": "458.p.64505",
    "player_id": "64505",
    "name": "Josh Caron",
    "first_name": "Josh",
    "last_name": "Caron",
    "position": "C",
    "eligible_positions": [],
    "team": "SEA",
    "team_full": "Seattle Mariners",
    "status": "NA",
    "ownership_type": "freeagents",
    "owned_by": null,
    "percent_owned": 0,
    "stats": {
      "stat_60": "-/-",
      "stat_7": "-",
      "stat_8": "-",
      "stat_12": "-",
      "stat_13": "-",
      "stat_16": "-",
      "stat_18": "-",
      "stat_21": "-",
      "stat_23": "-",
      "stat_3": "-",
      "stat_55": "-"
    }
  },
  {
    "player_key": "458.p.64507",
    "player_id": "64507",
    "name": "Ryan Campos",
    "first_name": "Ryan",
    "last_name": "Campos",
    "position": "C",
    "eligible_positions": [],
    "team": "STL",
    "team_full": "St. Louis Cardinals",
    "status": "NA",
    "ownership_type": "freeagents",
    "owned_by": null,
    "percent_owned": 0,
    "stats": {
      "stat_60": "-/-",
      "stat_7": "-",
      "stat_8": "-",
      "stat_12": "-",
      "stat_13": "-",
      "stat_16": "-",
      "stat_18": "-",
      "stat_21": "-",
      "stat_23": "-",
      "stat_3": "-",
      "stat_55": "-"
    }
  },
  {
    "player_key": "458.p.64525",
    "player_id": "64525",
    "name": "Nick Montgomery",
    "first_name": "Nick",
    "last_name": "Montgomery",
    "position": "C",
    "eligible_positions": [],
    "team": "ATL",
    "team_full": "Atlanta Braves",
    "status": "NA",
    "ownership_type": "freeagents",
    "owned_by": null,
    "percent_owned": 0,
    "stats": {
      "stat_60": "-/-",
      "stat_7": "-",
      "stat_8": "-",
      "stat_12": "-",
      "stat_13": "-",
      "stat_16": "-",
      "stat_18": "-",
      "stat_21": "-",
      "stat_23": "-",
      "stat_3": "-",
      "stat_55": "-"
    }
  },
  {
    "player_key": "458.p.64551",
    "player_id": "64551",
    "name": "Ivan Luciano",
    "first_name": "Ivan",
    "last_name": "Luciano",
    "position": "C",
    "eligible_positions": [],
    "team": "AZ",
    "team_full": "Arizona Diamondbacks",
    "status": "NA",
    "ownership_type": "freeagents",
    "owned_by": null,
    "percent_owned": 0,
    "stats": {
      "stat_60": "-/-",
      "stat_7": "-",
      "stat_8": "-",
      "stat_12": "-",
      "stat_13": "-",
      "stat_16": "-",
      "stat_18": "-",
      "stat_21": "-",
      "stat_23": "-",
      "stat_3": "-",
      "stat_55": "-"
    }
  },
  {
    "player_key": "458.p.64916",
    "player_id": "64916",
    "name": "Rainiel Rodriguez",
    "first_name": "Rainiel",
    "last_name": "Rodriguez",
    "position": "C",
    "eligible_positions": [],
    "team": "STL",
    "team_full": "St. Louis Cardinals",
    "status": "NA",
    "ownership_type": "freeagents",
    "owned_by": null,
    "percent_owned": 0,
    "stats": {
      "stat_60": "-/-",
      "stat_7": "-",
      "stat_8": "-",
      "stat_12": "-",
      "stat_13": "-",
      "stat_16": "-",
      "stat_18": "-",
      "stat_21": "-",
      "stat_23": "-",
      "stat_3": "-",
      "stat_55": "-"
    }
  },
  {
    "player_key": "458.p.64924",
    "player_id": "64924",
    "name": "Alberto Barriga",
    "first_name": "Alberto",
    "last_name": "Barriga",
    "position": "C",
    "eligible_positions": [],
    "team": "AZ",
    "team_full": "Arizona Diamondbacks",
    "status": "NA",
    "ownership_type": "freeagents",
    "owned_by": null,
    "percent_owned": 0,
    "stats": {
      "stat_60": "-/-",
      "stat_7": "-",
      "stat_8": "-",
      "stat_12": "-",
      "stat_13": "-",
      "stat_16": "-",
      "stat_18": "-",
      "stat_21": "-",
      "stat_23": "-",
      "stat_3": "-",
      "stat_55": "-"
    }
  },
  {
    "player_key": "458.p.64960",
    "player_id": "64960",
    "name": "Ramon Ramirez",
    "first_name": "Ramon",
    "last_name": "Ramirez",
    "position": "C",
    "eligible_positions": [],
    "team": "KC",
    "team_full": "Kansas City Royals",
    "status": "NA",
    "ownership_type": "freeagents",
    "owned_by": null,
    "percent_owned": 0,
    "stats": {
      "stat_60": "-/-",
      "stat_7": "-",
      "stat_8": "-",
      "stat_12": "-",
      "stat_13": "-",
      "stat_16": "-",
      "stat_18": "-",
      "stat_21": "-",
      "stat_23": "-",
      "stat_3": "-",
      "stat_55": "-"
    }
  },
  {
    "player_key": "458.p.64965",
    "player_id": "64965",
    "name": "Hyungchan Um",
    "first_name": "Hyungchan",
    "last_name": "Um",
    "position": "C",
    "eligible_positions": [],
    "team": "KC",
    "team_full": "Kansas City Royals",
    "status": "NA",
    "ownership_type": "freeagents",
    "owned_by": null,
    "percent_owned": 0,
    "stats": {
      "stat_60": "-/-",
      "stat_7": "-",
      "stat_8": "-",
      "stat_12": "-",
      "stat_13": "-",
      "stat_16": "-",
      "stat_18": "-",
      "stat_21": "-",
      "stat_23": "-",
      "stat_3": "-",
      "stat_55": "-"
    }
  },
  {
    "player_key": "458.p.64979",
    "player_id": "64979",
    "name": "Daiverson Gutierrez",
    "first_name": "Daiverson",
    "last_name": "Gutierrez",
    "position": "C",
    "eligible_positions": [],
    "team": "NYM",
    "team_full": "New York Mets",
    "status": "NA",
    "ownership_type": "freeagents",
    "owned_by": null,
    "percent_owned": 0,
    "stats": {
      "stat_60": "-/-",
      "stat_7": "-",
      "stat_8": "-",
      "stat_12": "-",
      "stat_13": "-",
      "stat_16": "-",
      "stat_18": "-",
      "stat_21": "-",
      "stat_23": "-",
      "stat_3": "-",
      "stat_55": "-"
    }
  },
  {
    "player_key": "458.p.64981",
    "player_id": "64981",
    "name": "Yovanny Rodriguez",
    "first_name": "Yovanny",
    "last_name": "Rodriguez",
    "position": "C",
    "eligible_positions": [],
    "team": "NYM",
    "team_full": "New York Mets",
    "status": "NA",
    "ownership_type": "freeagents",
    "owned_by": null,
    "percent_owned": 0,
    "stats": {
      "stat_60": "-/-",
      "stat_7": "-",
      "stat_8": "-",
      "stat_12": "-",
      "stat_13": "-",
      "stat_16": "-",
      "stat_18": "-",
      "stat_21": "-",
      "stat_23": "-",
      "stat_3": "-",
      "stat_55": "-"
    }
  },
  {
    "player_key": "458.p.64983",
    "player_id": "64983",
    "name": "Edgleen Perez",
    "first_name": "Edgleen",
    "last_name": "Perez",
    "position": "C",
    "eligible_positions": [],
    "team": "PIT",
    "team_full": "Pittsburgh Pirates",
    "status": "NA",
    "ownership_type": "freeagents",
    "owned_by": null,
    "percent_owned": 0,
    "stats": {
      "stat_60": "-/-",
      "stat_7": "-",
      "stat_8": "-",
      "stat_12": "-",
      "stat_13": "-",
      "stat_16": "-",
      "stat_18": "-",
      "stat_21": "-",
      "stat_23": "-",
      "stat_3": "-",
      "stat_55": "-"
    }
  },
  {
    "player_key": "458.p.64990",
    "player_id": "64990",
    "name": "Alirio Ferrebus",
    "first_name": "Alirio",
    "last_name": "Ferrebus",
    "position": "C",
    "eligible_positions": [],
    "team": "PHI",
    "team_full": "Philadelphia Phillies",
    "status": "NA",
    "ownership_type": "freeagents",
    "owned_by": null,
    "percent_owned": 0,
    "stats": {
      "stat_60": "-/-",
      "stat_7": "-",
      "stat_8": "-",
      "stat_12": "-",
      "stat_13": "-",
      "stat_16": "-",
      "stat_18": "-",
      "stat_21": "-",
      "stat_23": "-",
      "stat_3": "-",
      "stat_55": "-"
    }
  },
  {
    "player_key": "458.p.64998",
    "player_id": "64998",
    "name": "Yohendry Sanchez",
    "first_name": "Yohendry",
    "last_name": "Sanchez",
    "position": "C",
    "eligible_positions": [],
    "team": "SF",
    "team_full": "San Francisco Giants",
    "status": "NA",
    "ownership_type": "freeagents",
    "owned_by": null,
    "percent_owned": 0,
    "stats": {
      "stat_60": "-/-",
      "stat_7": "-",
      "stat_8": "-",
      "stat_12": "-",
      "stat_13": "-",
      "stat_16": "-",
      "stat_18": "-",
      "stat_21": "-",
      "stat_23": "-",
      "stat_3": "-",
      "stat_55": "-"
    }
  }
]